{"date": "2026-03-16", "teams": {"3997_909_2026": null, "4102_909_2026": null, "21138_909_2026": null, "18740_909_2026": null, "4019_909_2026": null, "10282_909_2026": null, "4028_909_2026": null, "8408_422_2026": null, "8403_422_2026": null, "18814_909_2026": null, "8417_422_2026": null, "10084_422_2026": null, "8410_422_2026": null, "15721_712_2026": null, "26893_712_2026": null, "8420_422_2026": null, "15722_712_2026": null, "22940_712_2026": null, "15726_712_2026": null, "15719_712_2026": null, "15718_712_2026": null, "15727_712_2026": null, "15723_712_2026": null, "15724_712_2026": null, "15729_712_2026": null, "3442_322_2025": {"scored": 10, "conceded": 4, "total": 14, "qualifies": true}, "3447_322_2025": {"scored": 8, "conceded": 2, "total": 10, "qualifies": false}, "25713_712_2026": null, "6407_322_2025": {"scored": 3, "conceded": 6, "total": 9, "qualifies": false}, "3441_322_2025": {"scored": 5, "conceded": 5, "total": 10, "qualifies": false}, "26495_322_2025": {"scored": 5, "conceded": 9, "total": 14, "qualifies": true}, "3436_322_2025": {"scored": 3, "conceded": 6, "total": 9, "qualifies": false}, "3445_322_2025": {"scored": 6, "conceded": 9, "total": 15, "qualifies": true}, "3438_322_2025": {"scored": 6, "conceded": 10, "total": 16, "qualifies": true}, "25020_322_2025": {"scored": 7, "conceded": 2, "total": 9, "qualifies": false}, "22606_322_2025": {"scored": 8, "conceded": 9, "total": 17, "qualifies": true}, "452_128_2026": {"scored": 5, "conceded": 5, "total": 10, "qualifies": false}, "441_128_2026": {"scored": 10, "conceded": 6, "total": 16, "qualifies": true}, "3443_322_2025": {"scored": 8, "conceded": 5, "total": 13, "qualifies": true}, "458_128_2026": {"scored": 3, "conceded": 3, "total": 6, "qualifies": false}, "451_128_2026": {"scored": 5, "conceded": 2, "total": 7, "qualifies": false}, "463_128_2026": {"scored": 2, "conceded": 6, "total": 8, "qualifies": false}, "2432_128_2026": {"scored": 5, "conceded": 6, "total": 11, "qualifies": false}, "460_128_2026": {"scored": 4, "conceded": 2, "total": 6, "qualifies": false}, "445_128_2026": {"scored": 5, "conceded": 5, "total": 10, "qualifies": false}, "455_128_2026": {"scored": 7, "conceded": 9, "total": 16, "qualifies": true}, "442_128_2026": {"scored": 4, "conceded": 4, "total": 8, "qualifies": false}, "436_128_2026": {"scored": 6, "conceded": 1, "total": 7, "qualifies": false}, "478_128_2026": {"scored": 6, "conceded": 6, "total": 12, "qualifies": true}, "446_128_2026": {"scored": 3, "conceded": 7, "total": 10, "qualifies": false}, "2424_128_2026": {"scored": 2, "conceded": 8, "total": 10, "qualifies": false}, "453_128_2026": {"scored": 11, "conceded": 8, "total": 19, "qualifies": true}, "457_128_2026": {"scored": 2, "conceded": 9, "total": 11, "qualifies": false}, "1065_128_2026": {"scored": 3, "conceded": 5, "total": 8, "qualifies": false}, "1066_128_2026": {"scored": 3, "conceded": 5, "total": 8, "qualifies": false}, "476_128_2026": {"scored": 1, "conceded": 1, "total": 2, "qualifies": false}, "2287_262_2025": {"scored": 8, "conceded": 8, "total": 16, "qualifies": true}, "450_128_2026": {"scored": 3, "conceded": 2, "total": 5, "qualifies": false}, "1135_239_2026": {"scored": 6, "conceded": 8, "total": 14, "qualifies": true}, "14002_262_2025": {"scored": 9, "conceded": 8, "total": 17, "qualifies": true}, "1464_239_2026": {"scored": 6, "conceded": 7, "total": 13, "qualifies": true}, "1147_239_2026": {"scored": 8, "conceded": 11, "total": 19, "qualifies": true}, "1470_239_2026": {"scored": 6, "conceded": 10, "total": 16, "qualifies": true}, "1131_239_2026": {"scored": 5, "conceded": 1, "total": 6, "qualifies": false}, "1125_239_2026": {"scored": 12, "conceded": 7, "total": 19, "qualifies": true}, "1126_239_2026": {"scored": 10, "conceded": 9, "total": 19, "qualifies": true}, "1136_239_2026": {"scored": 14, "conceded": 6, "total": 20, "qualifies": true}, "1137_239_2026": {"scored": 10, "conceded": 3, "total": 13, "qualifies": true}, "1132_239_2026": {"scored": 8, "conceded": 7, "total": 15, "qualifies": true}, "1134_239_2026": {"scored": 5, "conceded": 4, "total": 9, "qualifies": false}, "1462_239_2026": {"scored": 4, "conceded": 12, "total": 16, "qualifies": true}, "11682_234_2025": {"scored": 6, "conceded": 12, "total": 18, "qualifies": true}, "1051_234_2025": {"scored": 9, "conceded": 4, "total": 13, "qualifies": true}, "14884_673_2025": {"scored": 10, "conceded": 2, "total": 12, "qualifies": true}, "1057_234_2025": {"scored": 8, "conceded": 7, "total": 15, "qualifies": true}, "19456_234_2025": {"scored": 7, "conceded": 4, "total": 11, "qualifies": false}, "14871_673_2025": {"scored": 5, "conceded": 11, "total": 16, "qualifies": true}, "14873_673_2025": {"scored": 12, "conceded": 13, "total": 25, "qualifies": true}, "14868_673_2025": {"scored": 10, "conceded": 8, "total": 18, "qualifies": true}, "14879_673_2025": {"scored": 13, "conceded": 1, "total": 14, "qualifies": true}, "14877_673_2025": {"scored": 15, "conceded": 9, "total": 24, "qualifies": true}, "14885_673_2025": {"scored": 10, "conceded": 5, "total": 15, "qualifies": true}, "14878_673_2025": {"scored": 3, "conceded": 7, "total": 10, "qualifies": false}, "14883_673_2025": {"scored": 5, "conceded": 9, "total": 14, "qualifies": true}, "14872_673_2025": {"scored": 5, "conceded": 8, "total": 13, "qualifies": true}, "24090_588_2025": {"scored": 13, "conceded": 10, "total": 23, "qualifies": true}, "14875_673_2025": {"scored": 13, "conceded": 11, "total": 24, "qualifies": true}, "14870_673_2025": {"scored": 5, "conceded": 11, "total": 16, "qualifies": true}, "8017_588_2025": {"scored": 6, "conceded": 8, "total": 14, "qualifies": true}, "12527_588_2025": {"scored": 4, "conceded": 14, "total": 18, "qualifies": true}, "26331_588_2025": {"scored": 3, "conceded": 18, "total": 21, "qualifies": true}, "12528_588_2025": {"scored": 3, "conceded": 7, "total": 10, "qualifies": false}, "12526_588_2025": {"scored": 7, "conceded": 13, "total": 20, "qualifies": true}, "24091_588_2025": {"scored": 7, "conceded": 7, "total": 14, "qualifies": true}, "12523_588_2025": {"scored": 9, "conceded": 3, "total": 12, "qualifies": true}, "8015_588_2025": {"scored": 19, "conceded": 2, "total": 21, "qualifies": true}, "8013_588_2025": {"scored": 11, "conceded": 3, "total": 14, "qualifies": true}, "21010_389_2026": null, "12525_588_2025": {"scored": 1, "conceded": 5, "total": 6, "qualifies": false}, "12532_588_2025": {"scored": 9, "conceded": 4, "total": 13, "qualifies": true}, "4554_389_2026": null, "4565_389_2026": null, "21011_389_2026": null, "4564_389_2026": null, "2259_389_2026": null, "4544_389_2026": null, "4562_389_2026": null, "4560_389_2026": null, "664_389_2026": null, "562_389_2026": null, "16611_389_2026": null, "4563_389_2026": null, "4552_389_2026": null, "692_389_2026": null, "16781_836_2026": null, "4558_389_2026": null, "3584_204_2025": {"scored": 10, "conceded": 5, "total": 15, "qualifies": true}, "27510_836_2026": null, "6343_204_2025": {"scored": 11, "conceded": 4, "total": 15, "qualifies": true}, "17259_204_2025": {"scored": 6, "conceded": 9, "total": 15, "qualifies": true}, "3583_204_2025": {"scored": 11, "conceded": 12, "total": 23, "qualifies": true}, "7402_204_2025": {"scored": 14, "conceded": 5, "total": 19, "qualifies": true}, "3569_204_2025": {"scored": 5, "conceded": 9, "total": 14, "qualifies": true}, "3613_205_2025": {"scored": 7, "conceded": 9, "total": 16, "qualifies": true}, "6526_205_2025": {"scored": 2, "conceded": 13, "total": 15, "qualifies": true}, "3567_205_2025": {"scored": 8, "conceded": 9, "total": 17, "qualifies": true}, "3594_205_2025": {"scored": 2, "conceded": 4, "total": 6, "qualifies": false}, "7395_205_2025": {"scored": 15, "conceded": 3, "total": 18, "qualifies": true}, "7406_205_2025": {"scored": 6, "conceded": 7, "total": 13, "qualifies": true}, "26437_705_2025": {"scored": 3, "conceded": 4, "total": 7, "qualifies": false}, "24738_705_2025": {"scored": 7, "conceded": 4, "total": 11, "qualifies": false}, "24731_705_2025": {"scored": 10, "conceded": 8, "total": 18, "qualifies": true}, "24736_705_2025": {"scored": 10, "conceded": 5, "total": 15, "qualifies": true}, "24728_705_2025": {"scored": 7, "conceded": 6, "total": 13, "qualifies": true}, "24739_705_2025": {"scored": 11, "conceded": 5, "total": 16, "qualifies": true}, "13847_327_2026": null, "3499_327_2026": null, "705_327_2026": null, "685_327_2026": null, "14864_327_2026": null, "3683_342_2025": {"scored": 7, "conceded": 5, "total": 12, "qualifies": true}, "3686_342_2025": {"scored": 4, "conceded": 10, "total": 14, "qualifies": true}, "10017_327_2026": null, "6286_342_2025": {"scored": 9, "conceded": 7, "total": 16, "qualifies": true}, "3684_342_2025": {"scored": 7, "conceded": 7, "total": 14, "qualifies": true}, "9123_425_2025": {"scored": 4, "conceded": 11, "total": 15, "qualifies": true}, "27270_425_2025": {"scored": 4, "conceded": 6, "total": 10, "qualifies": false}, "24992_425_2025": {"scored": 5, "conceded": 12, "total": 17, "qualifies": true}, "9117_425_2025": {"scored": 6, "conceded": 2, "total": 8, "qualifies": false}, "10077_368_2025": {"scored": 2, "conceded": 19, "total": 21, "qualifies": true}, "9111_425_2025": {"scored": 7, "conceded": 4, "total": 11, "qualifies": false}, "8035_425_2025": {"scored": 7, "conceded": 3, "total": 10, "qualifies": false}, "4206_368_2025": {"scored": 14, "conceded": 2, "total": 16, "qualifies": true}, "11912_703_2025": {"scored": 6, "conceded": 11, "total": 17, "qualifies": true}, "20000_703_2025": {"scored": 15, "conceded": 9, "total": 24, "qualifies": true}, "20096_703_2025": {"scored": 15, "conceded": 15, "total": 30, "qualifies": true}, "20091_703_2025": {"scored": 10, "conceded": 4, "total": 14, "qualifies": true}, "20080_703_2025": {"scored": 7, "conceded": 10, "total": 17, "qualifies": true}, "20093_703_2025": {"scored": 5, "conceded": 10, "total": 15, "qualifies": true}, "20082_703_2025": {"scored": 10, "conceded": 5, "total": 15, "qualifies": true}, "20095_703_2025": {"scored": 3, "conceded": 12, "total": 15, "qualifies": true}, "20018_703_2025": {"scored": 10, "conceded": 10, "total": 20, "qualifies": true}, "20017_703_2025": {"scored": 14, "conceded": 11, "total": 25, "qualifies": true}, "20085_703_2025": {"scored": 4, "conceded": 10, "total": 14, "qualifies": true}, "20086_703_2025": {"scored": 8, "conceded": 10, "total": 18, "qualifies": true}, "20079_703_2025": {"scored": 13, "conceded": 9, "total": 22, "qualifies": true}, "20016_703_2025": {"scored": 7, "conceded": 4, "total": 11, "qualifies": false}, "20092_703_2025": {"scored": 5, "conceded": 12, "total": 17, "qualifies": true}, "20083_703_2025": {"scored": 11, "conceded": 12, "total": 23, "qualifies": true}, "22173_703_2025": {"scored": 11, "conceded": 12, "total": 23, "qualifies": true}, "20084_703_2025": {"scored": 9, "conceded": 9, "total": 18, "qualifies": true}, "26334_566_2025": {"scored": 5, "conceded": 21, "total": 26, "qualifies": true}, "26333_566_2025": {"scored": 2, "conceded": 17, "total": 19, "qualifies": true}, "12180_566_2025": {"scored": 10, "conceded": 4, "total": 14, "qualifies": true}, "12177_566_2025": {"scored": 5, "conceded": 7, "total": 12, "qualifies": true}, "22544_847_2025": {"scored": 2, "conceded": 5, "total": 7, "qualifies": false}, "22153_371_2025": {"scored": 5, "conceded": 3, "total": 8, "qualifies": false}, "6421_847_2025": {"scored": 2, "conceded": 3, "total": 5, "qualifies": false}, "4331_371_2025": {"scored": 5, "conceded": 5, "total": 10, "qualifies": false}, "663_371_2025": {"scored": 9, "conceded": 9, "total": 18, "qualifies": true}, "3466_323_2025": null, "693_371_2025": {"scored": 2, "conceded": 5, "total": 7, "qualifies": false}, "4376_374_2025": {"scored": 9, "conceded": 5, "total": 14, "qualifies": true}, "3475_323_2025": null, "24512_399_2026": {"scored": 4, "conceded": 6, "total": 10, "qualifies": false}, "16302_374_2025": {"scored": 1, "conceded": 10, "total": 11, "qualifies": false}, "5315_405_2025": {"scored": 4, "conceded": 9, "total": 13, "qualifies": true}, "5192_399_2026": {"scored": 8, "conceded": 4, "total": 12, "qualifies": true}, "5323_405_2025": {"scored": 6, "conceded": 4, "total": 10, "qualifies": false}, "5322_405_2025": {"scored": 2, "conceded": 4, "total": 6, "qualifies": false}, "16526_411_2026": {"scored": 3, "conceded": 6, "total": 9, "qualifies": false}, "5239_405_2025": {"scored": 6, "conceded": 3, "total": 9, "qualifies": false}, "5401_411_2026": {"scored": 10, "conceded": 5, "total": 15, "qualifies": true}, "20800_411_2026": {"scored": 10, "conceded": 6, "total": 16, "qualifies": true}, "15566_411_2026": {"scored": 4, "conceded": 4, "total": 8, "qualifies": false}, "16524_411_2026": {"scored": 8, "conceded": 4, "total": 12, "qualifies": true}, "5564_411_2026": {"scored": 3, "conceded": 6, "total": 9, "qualifies": false}, "5556_411_2026": {"scored": 7, "conceded": 10, "total": 17, "qualifies": true}, "5414_411_2026": {"scored": 6, "conceded": 6, "total": 12, "qualifies": true}, "20799_411_2026": {"scored": 4, "conceded": 10, "total": 14, "qualifies": true}, "5409_411_2026": {"scored": 7, "conceded": 6, "total": 13, "qualifies": true}, "5405_411_2026": {"scored": 7, "conceded": 8, "total": 15, "qualifies": true}, "5410_411_2026": {"scored": 6, "conceded": 7, "total": 13, "qualifies": true}, "5400_411_2026": {"scored": 3, "conceded": 3, "total": 6, "qualifies": false}, "5560_411_2026": {"scored": 10, "conceded": 8, "total": 18, "qualifies": true}, "2655_286_2025": {"scored": 4, "conceded": 13, "total": 17, "qualifies": true}, "2581_283_2025": {"scored": 6, "conceded": 9, "total": 15, "qualifies": true}, "2599_283_2025": {"scored": 16, "conceded": 6, "total": 22, "qualifies": true}, "2633_286_2025": {"scored": 5, "conceded": 3, "total": 8, "qualifies": false}, "2246_283_2025": {"scored": 10, "conceded": 4, "total": 14, "qualifies": true}, "6916_283_2025": {"scored": 3, "conceded": 7, "total": 10, "qualifies": false}, "1430_172_2025": {"scored": 3, "conceded": 2, "total": 5, "qualifies": false}, "1416_172_2025": {"scored": 9, "conceded": 10, "total": 19, "qualifies": true}, "856_172_2025": {"scored": 3, "conceded": 6, "total": 9, "qualifies": false}, "3517_328_2026": null, "1427_172_2025": {"scored": 5, "conceded": 4, "total": 9, "qualifies": false}, "26909_760_2025": {"scored": 8, "conceded": 8, "total": 16, "qualifies": true}, "25755_328_2026": null, "19890_760_2025": {"scored": 5, "conceded": 16, "total": 21, "qualifies": true}, "22358_760_2025": {"scored": 5, "conceded": 8, "total": 13, "qualifies": true}, "26907_760_2025": {"scored": 5, "conceded": 9, "total": 14, "qualifies": true}, "4048_760_2025": {"scored": 6, "conceded": 4, "total": 10, "qualifies": false}, "3985_236_2025": {"scored": 5, "conceded": 4, "total": 9, "qualifies": false}, "26908_760_2025": {"scored": 12, "conceded": 5, "total": 17, "qualifies": true}, "766_667_2026": {"scored": 8, "conceded": 9, "total": 17, "qualifies": true}, "2001_236_2025": {"scored": 8, "conceded": 3, "total": 11, "qualifies": false}, "12601_667_2026": null, "689_667_2026": null, "2082_667_2026": null, "2153_667_2026": {"scored": 9, "conceded": 8, "total": 17, "qualifies": true}, "2075_667_2026": null, "2085_667_2026": null, "6993_667_2026": null, "2170_667_2026": {"scored": 9, "conceded": 3, "total": 12, "qualifies": true}, "3733_346_2025": {"scored": 11, "conceded": 2, "total": 13, "qualifies": true}, "3412_318_2025": {"scored": 6, "conceded": 6, "total": 12, "qualifies": true}, "11674_667_2026": null, "4257_346_2025": {"scored": 11, "conceded": 5, "total": 16, "qualifies": true}, "614_318_2025": {"scored": 7, "conceded": 5, "total": 12, "qualifies": true}, "3424_318_2025": {"scored": 8, "conceded": 10, "total": 18, "qualifies": true}, "3399_318_2025": {"scored": 0, "conceded": 14, "total": 14, "qualifies": true}, "2871_301_2025": {"scored": 11, "conceded": 4, "total": 15, "qualifies": true}, "2867_301_2025": {"scored": 5, "conceded": 8, "total": 13, "qualifies": true}, "4912_301_2025": {"scored": 9, "conceded": 12, "total": 21, "qualifies": true}, "2870_301_2025": {"scored": 16, "conceded": 4, "total": 20, "qualifies": true}, "2876_301_2025": {"scored": 6, "conceded": 12, "total": 18, "qualifies": true}, "2875_301_2025": {"scored": 6, "conceded": 6, "total": 12, "qualifies": true}, "2874_301_2025": {"scored": 8, "conceded": 15, "total": 23, "qualifies": true}, "2879_301_2025": {"scored": 11, "conceded": 8, "total": 19, "qualifies": true}, "2865_301_2025": {"scored": 10, "conceded": 5, "total": 15, "qualifies": true}, "2877_301_2025": {"scored": 7, "conceded": 5, "total": 12, "qualifies": true}, "10155_301_2025": {"scored": 7, "conceded": 6, "total": 13, "qualifies": true}, "9136_301_2025": {"scored": 4, "conceded": 5, "total": 9, "qualifies": false}, "2872_301_2025": {"scored": 3, "conceded": 6, "total": 9, "qualifies": false}, "348_106_2025": {"scored": 4, "conceded": 3, "total": 7, "qualifies": false}, "336_106_2025": {"scored": 4, "conceded": 8, "total": 12, "qualifies": true}, "2873_301_2025": {"scored": 5, "conceded": 12, "total": 17, "qualifies": true}, "346_106_2025": {"scored": 6, "conceded": 7, "total": 13, "qualifies": true}, "3484_106_2025": {"scored": 8, "conceded": 4, "total": 12, "qualifies": true}, "586_362_2026": null, "2073_119_2025": {"scored": 2, "conceded": 14, "total": 16, "qualifies": true}, "18878_362_2026": null, "395_119_2025": {"scored": 8, "conceded": 11, "total": 19, "qualifies": true}, "2878_406_2025": {"scored": 4, "conceded": 1, "total": 5, "qualifies": false}, "5334_406_2025": {"scored": 5, "conceded": 10, "total": 15, "qualifies": true}, "5329_406_2025": {"scored": 14, "conceded": 3, "total": 17, "qualifies": true}, "11380_406_2025": {"scored": 3, "conceded": 10, "total": 13, "qualifies": true}, "5335_406_2025": {"scored": 2, "conceded": 9, "total": 11, "qualifies": false}, "15962_406_2025": {"scored": 7, "conceded": 6, "total": 13, "qualifies": true}, "5328_406_2025": {"scored": 4, "conceded": 11, "total": 15, "qualifies": true}, "5330_406_2025": {"scored": 3, "conceded": 4, "total": 7, "qualifies": false}, "7505_406_2025": {"scored": 13, "conceded": 7, "total": 20, "qualifies": true}, "5336_406_2025": {"scored": 4, "conceded": 4, "total": 8, "qualifies": false}, "5337_406_2025": {"scored": 3, "conceded": 3, "total": 6, "qualifies": false}, "7504_406_2025": {"scored": 7, "conceded": 1, "total": 8, "qualifies": false}, "15960_406_2025": {"scored": 5, "conceded": 8, "total": 13, "qualifies": true}, "5327_406_2025": {"scored": 5, "conceded": 5, "total": 10, "qualifies": false}, "8393_132_2026": null, "1931_132_2026": null, "243_95_2025": {"scored": 10, "conceded": 5, "total": 15, "qualifies": true}, "8398_132_2026": null, "8374_132_2026": null, "233_95_2025": {"scored": 6, "conceded": 11, "total": 17, "qualifies": true}, "4799_95_2025": {"scored": 7, "conceded": 4, "total": 11, "qualifies": false}, "421_89_2025": {"scored": 9, "conceded": 9, "total": 18, "qualifies": true}, "216_95_2025": {"scored": 6, "conceded": 10, "total": 16, "qualifies": true}, "411_89_2025": {"scored": 8, "conceded": 7, "total": 15, "qualifies": true}, "424_89_2025": {"scored": 4, "conceded": 10, "total": 14, "qualifies": true}, "418_89_2025": {"scored": 8, "conceded": 9, "total": 17, "qualifies": true}, "420_89_2025": {"scored": 9, "conceded": 5, "total": 14, "qualifies": true}, "412_89_2025": {"scored": 6, "conceded": 10, "total": 16, "qualifies": true}, "414_89_2025": {"scored": 7, "conceded": 6, "total": 13, "qualifies": true}, "200_89_2025": {"scored": 9, "conceded": 9, "total": 18, "qualifies": true}, "419_89_2025": {"scored": 11, "conceded": 9, "total": 20, "qualifies": true}, "198_89_2025": {"scored": 6, "conceded": 2, "total": 8, "qualifies": false}, "417_89_2025": {"scored": 9, "conceded": 5, "total": 14, "qualifies": true}, "428_89_2025": {"scored": 3, "conceded": 6, "total": 9, "qualifies": false}, "409_89_2025": {"scored": 4, "conceded": 5, "total": 9, "qualifies": false}, "204_89_2025": {"scored": 4, "conceded": 9, "total": 13, "qualifies": true}, "423_89_2025": {"scored": 4, "conceded": 10, "total": 14, "qualifies": true}, "2389_272_2025": {"scored": 4, "conceded": 5, "total": 9, "qualifies": false}, "425_89_2025": {"scored": 10, "conceded": 5, "total": 15, "qualifies": true}, "1919_142_2025": {"scored": 3, "conceded": 8, "total": 11, "qualifies": false}, "675_272_2025": {"scored": 11, "conceded": 0, "total": 11, "qualifies": false}, "15225_142_2025": {"scored": 1, "conceded": 12, "total": 13, "qualifies": true}, "7197_702_2025": {"scored": 22, "conceded": 1, "total": 23, "qualifies": true}, "14430_702_2025": {"scored": 5, "conceded": 17, "total": 22, "qualifies": true}, "20081_702_2025": {"scored": 8, "conceded": 10, "total": 18, "qualifies": true}, "7196_702_2025": {"scored": 17, "conceded": 6, "total": 23, "qualifies": true}, "7202_702_2025": {"scored": 11, "conceded": 10, "total": 21, "qualifies": true}, "7191_702_2025": {"scored": 10, "conceded": 11, "total": 21, "qualifies": true}, "10861_521_2026": {"scored": 10, "conceded": 5, "total": 15, "qualifies": true}, "1145_240_2026": {"scored": 4, "conceded": 7, "total": 11, "qualifies": false}, "15622_521_2026": {"scored": 7, "conceded": 5, "total": 12, "qualifies": true}, "1468_240_2026": {"scored": 3, "conceded": 7, "total": 10, "qualifies": false}, "1465_240_2026": {"scored": 12, "conceded": 5, "total": 17, "qualifies": true}, "1129_240_2026": {"scored": 7, "conceded": 4, "total": 11, "qualifies": false}, "1140_240_2026": {"scored": 3, "conceded": 3, "total": 6, "qualifies": false}, "1459_240_2026": {"scored": 12, "conceded": 6, "total": 18, "qualifies": true}, "7868_521_2026": {"scored": 6, "conceded": 8, "total": 14, "qualifies": true}, "1466_240_2026": {"scored": 3, "conceded": 9, "total": 12, "qualifies": true}, "23326_240_2026": {"scored": 11, "conceded": 5, "total": 16, "qualifies": true}, "2231_521_2026": {"scored": 6, "conceded": 5, "total": 11, "qualifies": false}, "1458_240_2026": {"scored": 5, "conceded": 3, "total": 8, "qualifies": false}, "27411_240_2026": {"scored": 8, "conceded": 3, "total": 11, "qualifies": false}, "1461_240_2026": {"scored": 6, "conceded": 4, "total": 10, "qualifies": false}, "4539_387_2025": {"scored": 3, "conceded": 4, "total": 7, "qualifies": false}, "4535_387_2025": {"scored": 6, "conceded": 7, "total": 13, "qualifies": true}, "22099_240_2026": {"scored": 5, "conceded": 6, "total": 11, "qualifies": false}, "4529_387_2025": {"scored": 5, "conceded": 9, "total": 14, "qualifies": true}, "4534_387_2025": {"scored": 4, "conceded": 7, "total": 11, "qualifies": false}, "4531_387_2025": {"scored": 10, "conceded": 2, "total": 12, "qualifies": true}, "4533_387_2025": {"scored": 10, "conceded": 4, "total": 14, "qualifies": true}, "17469_387_2025": {"scored": 3, "conceded": 11, "total": 14, "qualifies": true}, "4530_387_2025": {"scored": 11, "conceded": 16, "total": 27, "qualifies": true}, "4532_387_2025": {"scored": 18, "conceded": 7, "total": 25, "qualifies": true}, "4537_387_2025": {"scored": 7, "conceded": 8, "total": 15, "qualifies": true}, "722_141_2025": {"scored": 3, "conceded": 5, "total": 8, "qualifies": false}, "1584_138_2025": {"scored": 7, "conceded": 5, "total": 12, "qualifies": true}, "520_135_2025": {"scored": 2, "conceded": 9, "total": 11, "qualifies": false}, "534_141_2025": {"scored": 9, "conceded": 2, "total": 11, "qualifies": false}, "26355_138_2025": {"scored": 4, "conceded": 6, "total": 10, "qualifies": false}, "502_135_2025": {"scored": 5, "conceded": 6, "total": 11, "qualifies": false}, "3012_62_2025": {"scored": 7, "conceded": 7, "total": 14, "qualifies": true}, "4689_51_2025": {"scored": 14, "conceded": 4, "total": 18, "qualifies": true}, "1838_51_2025": {"scored": 5, "conceded": 2, "total": 7, "qualifies": false}, "110_62_2025": {"scored": 9, "conceded": 6, "total": 15, "qualifies": true}, "4685_51_2025": {"scored": 9, "conceded": 9, "total": 18, "qualifies": true}, "1840_51_2025": {"scored": 10, "conceded": 7, "total": 17, "qualifies": true}, "4702_51_2025": {"scored": 6, "conceded": 6, "total": 12, "qualifies": true}, "7714_51_2025": {"scored": 2, "conceded": 11, "total": 13, "qualifies": true}, "7715_51_2025": {"scored": 7, "conceded": 8, "total": 15, "qualifies": true}, "7612_51_2025": {"scored": 5, "conceded": 5, "total": 10, "qualifies": false}, "8659_51_2025": {"scored": 7, "conceded": 5, "total": 12, "qualifies": true}, "1821_51_2025": {"scored": 3, "conceded": 4, "total": 7, "qualifies": false}, "7723_51_2025": {"scored": 3, "conceded": 7, "total": 10, "qualifies": false}, "4687_51_2025": {"scored": 4, "conceded": 6, "total": 10, "qualifies": false}, "8657_51_2025": {"scored": 4, "conceded": 12, "total": 16, "qualifies": true}, "3850_357_2026": {"scored": 6, "conceded": 9, "total": 15, "qualifies": true}, "8662_51_2025": {"scored": 4, "conceded": 3, "total": 7, "qualifies": false}, "584_357_2026": {"scored": 9, "conceded": 8, "total": 17, "qualifies": true}, "652_357_2026": {"scored": 8, "conceded": 6, "total": 14, "qualifies": true}, "3854_357_2026": {"scored": 9, "conceded": 8, "total": 17, "qualifies": true}, "3842_357_2026": {"scored": 2, "conceded": 8, "total": 10, "qualifies": false}, "3840_357_2026": {"scored": 10, "conceded": 2, "total": 12, "qualifies": true}, "3843_357_2026": {"scored": 12, "conceded": 5, "total": 17, "qualifies": true}, "3851_357_2026": {"scored": 4, "conceded": 5, "total": 9, "qualifies": false}, "670_357_2026": {"scored": 7, "conceded": 8, "total": 15, "qualifies": true}, "3845_357_2026": {"scored": 2, "conceded": 12, "total": 14, "qualifies": true}, "353_110_2025": {"scored": 3, "conceded": 6, "total": 9, "qualifies": false}, "55_39_2025": {"scored": 8, "conceded": 8, "total": 16, "qualifies": true}, "2201_110_2025": {"scored": 7, "conceded": 4, "total": 11, "qualifies": false}, "1355_40_2025": {"scored": 6, "conceded": 7, "total": 13, "qualifies": true}, "39_39_2025": {"scored": 6, "conceded": 4, "total": 10, "qualifies": false}, "38_40_2025": {"scored": 6, "conceded": 7, "total": 13, "qualifies": true}, "69_40_2025": {"scored": 7, "conceded": 9, "total": 16, "qualifies": true}, "41_40_2025": {"scored": 12, "conceded": 4, "total": 16, "qualifies": true}, "1837_40_2025": {"scored": 11, "conceded": 6, "total": 17, "qualifies": true}, "71_40_2025": {"scored": 9, "conceded": 3, "total": 12, "qualifies": true}, "728_140_2025": {"scored": 9, "conceded": 3, "total": 12, "qualifies": true}, "2352_268_2026": {"scored": 6, "conceded": 7, "total": 13, "qualifies": true}, "539_140_2025": {"scored": 3, "conceded": 7, "total": 10, "qualifies": false}, "2358_268_2026": {"scored": 7, "conceded": 4, "total": 11, "qualifies": false}, "2353_268_2026": {"scored": 6, "conceded": 7, "total": 13, "qualifies": true}, "2365_268_2026": {"scored": 9, "conceded": 5, "total": 14, "qualifies": true}, "2326_265_2026": {"scored": 6, "conceded": 6, "total": 12, "qualifies": true}, "2315_265_2026": {"scored": 5, "conceded": 1, "total": 6, "qualifies": false}, "2320_265_2026": {"scored": 5, "conceded": 7, "total": 12, "qualifies": true}, "132_71_2026": null, "2328_265_2026": {"scored": 8, "conceded": 8, "total": 16, "qualifies": true}, "130_71_2026": {"scored": 9, "conceded": 9, "total": 18, "qualifies": true}, "118_71_2026": {"scored": 6, "conceded": 3, "total": 9, "qualifies": false}, "121_71_2026": {"scored": 12, "conceded": 5, "total": 17, "qualifies": true}, "134_71_2026": {"scored": 6, "conceded": 6, "total": 12, "qualifies": true}, "794_71_2026": {"scored": 4, "conceded": 4, "total": 8, "qualifies": false}, "120_71_2026": null, "135_71_2026": {"scored": 4, "conceded": 11, "total": 15, "qualifies": true}, "1062_71_2026": {"scored": 5, "conceded": 8, "total": 13, "qualifies": true}, "7848_71_2026": {"scored": 8, "conceded": 8, "total": 16, "qualifies": true}, "126_71_2026": {"scored": 8, "conceded": 2, "total": 10, "qualifies": false}, "147_71_2026": {"scored": 8, "conceded": 5, "total": 13, "qualifies": true}, "2345_266_2026": null, "1948_129_2026": null, "2333_266_2026": null, "1954_129_2026": null, "17377_163_2025": {"scored": 8, "conceded": 7, "total": 15, "qualifies": true}, "20788_304_2026": {"scored": 8, "conceded": 8, "total": 16, "qualifies": true}, "26425_722_2025": {"scored": 4, "conceded": 11, "total": 15, "qualifies": true}, "2052_163_2025": {"scored": 6, "conceded": 7, "total": 13, "qualifies": true}, "27364_304_2026": {"scored": 6, "conceded": 3, "total": 9, "qualifies": false}, "15937_722_2025": {"scored": 11, "conceded": 10, "total": 21, "qualifies": true}, "22055_722_2025": {"scored": 9, "conceded": 2, "total": 11, "qualifies": false}, "15939_722_2025": {"scored": 6, "conceded": 11, "total": 17, "qualifies": true}, "26524_722_2025": {"scored": 6, "conceded": 9, "total": 15, "qualifies": true}, "943_188_2025": {"scored": 6, "conceded": 5, "total": 11, "qualifies": false}, "15938_722_2025": {"scored": 6, "conceded": 7, "total": 13, "qualifies": true}, "14433_335_2025": null, "945_188_2025": {"scored": 6, "conceded": 15, "total": 21, "qualifies": true}, "14441_335_2025": null, "2768_292_2026": null, "2745_292_2026": null, "2763_292_2026": null, "2759_292_2026": null, "2746_292_2026": null, "2750_292_2026": null, "2761_292_2026": null, "2762_292_2026": null, "2764_292_2026": null, "2748_292_2026": null, "2767_292_2026": null, "2766_292_2026": null, "26198_343_2025": {"scored": 13, "conceded": 3, "total": 16, "qualifies": true}, "18009_324_2025": null, "25114_343_2025": {"scored": 6, "conceded": 9, "total": 15, "qualifies": true}, "17171_343_2025": {"scored": 13, "conceded": 2, "total": 15, "qualifies": true}, "3469_324_2025": null, "3697_343_2025": {"scored": 4, "conceded": 19, "total": 23, "qualifies": true}, "3689_343_2025": {"scored": 4, "conceded": 11, "total": 15, "qualifies": true}, "21877_343_2025": {"scored": 13, "conceded": 9, "total": 22, "qualifies": true}, "26199_343_2025": {"scored": 5, "conceded": 12, "total": 17, "qualifies": true}, "11174_343_2025": {"scored": 5, "conceded": 13, "total": 18, "qualifies": true}, "24965_343_2025": {"scored": 5, "conceded": 8, "total": 13, "qualifies": true}, "20087_343_2025": {"scored": 13, "conceded": 4, "total": 17, "qualifies": true}, "14392_664_2025": {"scored": 3, "conceded": 6, "total": 9, "qualifies": false}, "14394_664_2025": {"scored": 6, "conceded": 6, "total": 12, "qualifies": true}, "15576_664_2025": {"scored": 7, "conceded": 5, "total": 12, "qualifies": true}, "14281_664_2025": {"scored": 7, "conceded": 4, "total": 11, "qualifies": false}, "14395_664_2025": {"scored": 6, "conceded": 8, "total": 14, "qualifies": true}, "680_664_2025": {"scored": 6, "conceded": 7, "total": 13, "qualifies": true}, "14393_664_2025": {"scored": 5, "conceded": 6, "total": 11, "qualifies": false}, "12772_664_2025": {"scored": 6, "conceded": 4, "total": 10, "qualifies": false}, "22816_664_2025": {"scored": 5, "conceded": 5, "total": 10, "qualifies": false}, "4569_390_2025": {"scored": 13, "conceded": 2, "total": 15, "qualifies": true}, "1070_186_2025": {"scored": 2, "conceded": 12, "total": 14, "qualifies": true}, "12733_664_2025": {"scored": 6, "conceded": 6, "total": 12, "qualifies": true}, "4567_390_2025": {"scored": 3, "conceded": 2, "total": 5, "qualifies": false}, "915_186_2025": {"scored": 9, "conceded": 16, "total": 25, "qualifies": true}, "10780_186_2025": {"scored": 9, "conceded": 5, "total": 14, "qualifies": true}, "906_186_2025": {"scored": 8, "conceded": 2, "total": 10, "qualifies": false}, "911_186_2025": {"scored": 4, "conceded": 0, "total": 4, "qualifies": false}, "10752_186_2025": {"scored": 8, "conceded": 8, "total": 16, "qualifies": true}, "907_186_2025": {"scored": 6, "conceded": 5, "total": 11, "qualifies": false}, "10792_186_2025": {"scored": 8, "conceded": 7, "total": 15, "qualifies": true}, "904_186_2025": {"scored": 5, "conceded": 2, "total": 7, "qualifies": false}, "10743_186_2025": {"scored": 2, "conceded": 4, "total": 6, "qualifies": false}, "10777_186_2025": {"scored": 5, "conceded": 8, "total": 13, "qualifies": true}, "931_186_2025": {"scored": 4, "conceded": 3, "total": 7, "qualifies": false}, "918_186_2025": {"scored": 7, "conceded": 6, "total": 13, "qualifies": true}, "910_186_2025": {"scored": 3, "conceded": 4, "total": 7, "qualifies": false}, "914_186_2025": {"scored": 6, "conceded": 2, "total": 8, "qualifies": false}, "11885_361_2026": null, "3857_361_2026": null, "3859_361_2026": null, "905_186_2025": {"scored": 5, "conceded": 4, "total": 9, "qualifies": false}, "18840_361_2026": null, "14384_361_2026": null, "3871_361_2026": null, "14382_361_2026": null, "16674_361_2026": null, "10696_361_2026": null, "27557_361_2026": null, "3864_361_2026": null, "3862_361_2026": null, "3856_361_2026": null, "23156_361_2026": null, "16747_361_2026": null, "13971_361_2026": null, "9132_782_2025": {"scored": 6, "conceded": 10, "total": 16, "qualifies": true}, "14267_782_2025": {"scored": 3, "conceded": 13, "total": 16, "qualifies": true}, "17401_782_2025": {"scored": 5, "conceded": 14, "total": 19, "qualifies": true}, "17402_782_2025": {"scored": 9, "conceded": 6, "total": 15, "qualifies": true}, "6963_782_2025": {"scored": 12, "conceded": 7, "total": 19, "qualifies": true}, "22910_782_2025": {"scored": 13, "conceded": 9, "total": 22, "qualifies": true}, "16263_782_2025": {"scored": 14, "conceded": 7, "total": 21, "qualifies": true}, "21658_782_2025": {"scored": 3, "conceded": 12, "total": 15, "qualifies": true}, "24659_1130_2025": {"scored": 5, "conceded": 2, "total": 7, "qualifies": false}, "26183_782_2025": {"scored": 5, "conceded": 7, "total": 12, "qualifies": true}, "12901_782_2025": {"scored": 12, "conceded": 4, "total": 16, "qualifies": true}, "24658_1130_2025": {"scored": 4, "conceded": 5, "total": 9, "qualifies": false}, "24663_1130_2025": {"scored": 7, "conceded": 7, "total": 14, "qualifies": true}, "3359_314_2025": null, "6938_781_2025": {"scored": 6, "conceded": 5, "total": 11, "qualifies": false}, "24657_1130_2025": {"scored": 7, "conceded": 9, "total": 16, "qualifies": true}, "19562_314_2025": null, "6959_781_2025": {"scored": 6, "conceded": 6, "total": 12, "qualifies": true}, "621_237_2025": {"scored": 11, "conceded": 4, "total": 15, "qualifies": true}, "596_237_2025": {"scored": 10, "conceded": 3, "total": 13, "qualifies": true}, "558_237_2025": {"scored": 13, "conceded": 10, "total": 23, "qualifies": true}, "555_237_2025": {"scored": 8, "conceded": 5, "total": 13, "qualifies": true}, "6813_237_2025": {"scored": 6, "conceded": 6, "total": 12, "qualifies": true}, "1088_237_2025": {"scored": 12, "conceded": 4, "total": 16, "qualifies": true}, "5553_403_2025": {"scored": 7, "conceded": 2, "total": 9, "qualifies": false}, "611_203_2025": {"scored": 9, "conceded": 9, "total": 18, "qualifies": true}, "996_203_2025": {"scored": 6, "conceded": 8, "total": 14, "qualifies": true}, "5288_403_2025": {"scored": 4, "conceded": 4, "total": 8, "qualifies": false}, "3573_203_2025": {"scored": 6, "conceded": 7, "total": 13, "qualifies": true}, "7411_203_2025": {"scored": 5, "conceded": 5, "total": 10, "qualifies": false}, "564_203_2025": {"scored": 8, "conceded": 8, "total": 16, "qualifies": true}, "3588_203_2025": {"scored": 2, "conceded": 7, "total": 9, "qualifies": false}, "1005_203_2025": {"scored": 6, "conceded": 9, "total": 15, "qualifies": true}, "10550_680_2025": {"scored": 21, "conceded": 3, "total": 24, "qualifies": true}, "998_203_2025": {"scored": 11, "conceded": 6, "total": 17, "qualifies": true}, "10534_680_2025": {"scored": 24, "conceded": 5, "total": 29, "qualifies": true}, "3554_680_2025": {"scored": 22, "conceded": 2, "total": 24, "qualifies": true}, "4495_382_2025": {"scored": 11, "conceded": 4, "total": 15, "qualifies": true}, "3548_680_2025": {"scored": 21, "conceded": 5, "total": 26, "qualifies": true}, "4503_382_2025": {"scored": 7, "conceded": 7, "total": 14, "qualifies": true}, "6192_382_2025": {"scored": 11, "conceded": 5, "total": 16, "qualifies": true}, "4491_382_2025": {"scored": 11, "conceded": 5, "total": 16, "qualifies": true}, "2699_288_2025": {"scored": 10, "conceded": 3, "total": 13, "qualifies": true}, "2690_288_2025": {"scored": 7, "conceded": 5, "total": 12, "qualifies": true}, "2682_288_2025": {"scored": 4, "conceded": 8, "total": 12, "qualifies": true}, "4905_288_2025": {"scored": 5, "conceded": 3, "total": 8, "qualifies": false}, "228_2_2025": {"scored": 9, "conceded": 9, "total": 18, "qualifies": true}, "50_2_2025": {"scored": 5, "conceded": 9, "total": 14, "qualifies": true}, "327_2_2025": {"scored": 13, "conceded": 4, "total": 17, "qualifies": true}, "49_2_2025": {"scored": 10, "conceded": 9, "total": 19, "qualifies": true}, "541_2_2025": {"scored": 14, "conceded": 6, "total": 20, "qualifies": true}, "85_2_2025": {"scored": 12, "conceded": 9, "total": 21, "qualifies": true}, "42_2_2025": {"scored": 13, "conceded": 5, "total": 18, "qualifies": true}, "529_2_2025": {"scored": 11, "conceded": 8, "total": 19, "qualifies": true}, "168_2_2025": {"scored": 6, "conceded": 3, "total": 9, "qualifies": false}, "40_2_2025": {"scored": 11, "conceded": 5, "total": 16, "qualifies": true}, "34_2_2025": {"scored": 14, "conceded": 5, "total": 19, "qualifies": true}, "47_2_2025": {"scored": 12, "conceded": 10, "total": 22, "qualifies": true}, "645_2_2025": {"scored": 9, "conceded": 8, "total": 17, "qualifies": true}, "530_2_2025": {"scored": 14, "conceded": 9, "total": 23, "qualifies": true}, "157_2_2025": {"scored": 14, "conceded": 6, "total": 20, "qualifies": true}, "12756_85_2025": {"scored": 3, "conceded": 8, "total": 11, "qualifies": false}, "499_2_2025": {"scored": 7, "conceded": 13, "total": 20, "qualifies": true}, "1651_85_2025": {"scored": 5, "conceded": 9, "total": 14, "qualifies": true}, "9358_85_2025": {"scored": 11, "conceded": 3, "total": 14, "qualifies": true}, "1618_85_2025": {"scored": 3, "conceded": 12, "total": 15, "qualifies": true}, "1314_83_2025": {"scored": 10, "conceded": 2, "total": 12, "qualifies": true}, "9323_83_2025": {"scored": 4, "conceded": 7, "total": 11, "qualifies": false}, "9324_83_2025": {"scored": 2, "conceded": 6, "total": 8, "qualifies": false}, "9328_83_2025": {"scored": 8, "conceded": 7, "total": 15, "qualifies": true}, "8365_221_2025": {"scored": 7, "conceded": 6, "total": 13, "qualifies": true}, "1397_221_2025": {"scored": 9, "conceded": 1, "total": 10, "qualifies": false}, "522_136_2025": {"scored": 7, "conceded": 6, "total": 13, "qualifies": true}, "8366_221_2025": {"scored": 10, "conceded": 5, "total": 15, "qualifies": true}, "4952_221_2025": {"scored": 8, "conceded": 6, "total": 14, "qualifies": true}, "863_136_2025": {"scored": 3, "conceded": 6, "total": 9, "qualifies": false}, "517_136_2025": {"scored": 10, "conceded": 3, "total": 13, "qualifies": true}, "1693_136_2025": {"scored": 8, "conceded": 6, "total": 14, "qualifies": true}, "515_136_2025": {"scored": 9, "conceded": 10, "total": 19, "qualifies": true}, "870_136_2025": {"scored": 6, "conceded": 8, "total": 14, "qualifies": true}, "509_136_2025": {"scored": 6, "conceded": 9, "total": 15, "qualifies": true}, "511_136_2025": {"scored": 8, "conceded": 10, "total": 18, "qualifies": true}, "880_136_2025": {"scored": 3, "conceded": 11, "total": 14, "qualifies": true}, "1687_136_2025": {"scored": 14, "conceded": 9, "total": 23, "qualifies": true}, "512_136_2025": {"scored": 11, "conceded": 8, "total": 19, "qualifies": true}, "1579_136_2025": {"scored": 11, "conceded": 5, "total": 16, "qualifies": true}, "899_136_2025": {"scored": 7, "conceded": 5, "total": 12, "qualifies": true}, "508_136_2025": {"scored": 9, "conceded": 7, "total": 16, "qualifies": true}, "1581_136_2025": {"scored": 5, "conceded": 7, "total": 12, "qualifies": true}, "525_136_2025": {"scored": 10, "conceded": 6, "total": 16, "qualifies": true}, "528_136_2025": {"scored": 4, "conceded": 6, "total": 10, "qualifies": false}, "498_136_2025": {"scored": 2, "conceded": 8, "total": 10, "qualifies": false}, "527_136_2025": {"scored": 5, "conceded": 8, "total": 13, "qualifies": true}, "1578_136_2025": {"scored": 5, "conceded": 5, "total": 10, "qualifies": false}, "275_168_2026": {"scored": 15, "conceded": 8, "total": 23, "qualifies": true}, "2116_168_2026": {"scored": 24, "conceded": 3, "total": 27, "qualifies": true}, "4165_168_2026": null, "11064_542_2025": {"scored": 10, "conceded": 5, "total": 15, "qualifies": true}, "267_168_2026": null, "11066_542_2025": {"scored": 2, "conceded": 8, "total": 10, "qualifies": false}, "11071_542_2025": {"scored": 4, "conceded": 8, "total": 12, "qualifies": true}, "8009_542_2025": {"scored": 9, "conceded": 3, "total": 12, "qualifies": true}, "11069_542_2025": {"scored": 2, "conceded": 11, "total": 13, "qualifies": true}, "26600_542_2025": {"scored": 6, "conceded": 10, "total": 16, "qualifies": true}, "8010_542_2025": {"scored": 6, "conceded": 8, "total": 14, "qualifies": true}, "5242_542_2025": {"scored": 8, "conceded": 4, "total": 12, "qualifies": true}, "26598_542_2025": {"scored": 3, "conceded": 5, "total": 8, "qualifies": false}, "11067_542_2025": {"scored": 8, "conceded": 3, "total": 11, "qualifies": false}, "15544_542_2025": {"scored": 7, "conceded": 4, "total": 11, "qualifies": false}, "11065_542_2025": {"scored": 6, "conceded": 6, "total": 12, "qualifies": true}, "25062_542_2025": {"scored": 8, "conceded": 5, "total": 13, "qualifies": true}, "11074_542_2025": {"scored": 5, "conceded": 7, "total": 12, "qualifies": true}, "25061_542_2025": {"scored": 3, "conceded": 6, "total": 9, "qualifies": false}, "15546_542_2025": {"scored": 1, "conceded": 10, "total": 11, "qualifies": false}, "20463_542_2025": {"scored": 7, "conceded": 7, "total": 14, "qualifies": true}, "15547_542_2025": {"scored": 8, "conceded": 4, "total": 12, "qualifies": true}, "1623_84_2025": {"scored": 11, "conceded": 5, "total": 16, "qualifies": true}, "11070_542_2025": {"scored": 11, "conceded": 6, "total": 17, "qualifies": true}, "25063_542_2025": {"scored": 9, "conceded": 6, "total": 15, "qualifies": true}, "14629_84_2025": {"scored": 2, "conceded": 6, "total": 8, "qualifies": false}, "1655_84_2025": {"scored": 9, "conceded": 10, "total": 19, "qualifies": true}, "9338_84_2025": {"scored": 7, "conceded": 15, "total": 22, "qualifies": true}, "1650_87_2025": {"scored": 4, "conceded": 9, "total": 13, "qualifies": true}, "9340_84_2025": {"scored": 9, "conceded": 6, "total": 15, "qualifies": true}, "1330_84_2025": {"scored": 5, "conceded": 5, "total": 10, "qualifies": false}, "9375_87_2025": {"scored": 3, "conceded": 14, "total": 17, "qualifies": true}, "3229_63_2025": {"scored": 8, "conceded": 11, "total": 19, "qualifies": true}, "2905_305_2025": {"scored": 8, "conceded": 8, "total": 16, "qualifies": true}, "107_63_2025": {"scored": 5, "conceded": 8, "total": 13, "qualifies": true}, "2897_305_2025": {"scored": 9, "conceded": 10, "total": 19, "qualifies": true}, "2895_305_2025": {"scored": 15, "conceded": 8, "total": 23, "qualifies": true}, "2900_305_2025": {"scored": 10, "conceded": 8, "total": 18, "qualifies": true}, "2916_305_2025": {"scored": 5, "conceded": 1, "total": 6, "qualifies": false}, "2903_305_2025": {"scored": 4, "conceded": 9, "total": 13, "qualifies": true}, "2904_305_2025": {"scored": 8, "conceded": 7, "total": 15, "qualifies": true}, "2898_305_2025": {"scored": 3, "conceded": 6, "total": 9, "qualifies": false}, "2896_305_2025": {"scored": 6, "conceded": 11, "total": 17, "qualifies": true}, "2899_305_2025": {"scored": 12, "conceded": 9, "total": 21, "qualifies": true}, "2893_305_2025": {"scored": 7, "conceded": 14, "total": 21, "qualifies": true}, "2907_305_2025": {"scored": 13, "conceded": 9, "total": 22, "qualifies": true}, "1830_1156_2025": null, "1367_42_2025": null, "7203_1156_2025": null, "1832_42_2025": null, "1360_42_2025": null, "1334_42_2025": null, "1372_42_2025": null, "1376_42_2025": null, "1352_42_2025": null, "1363_42_2025": null, "1345_42_2025": null, "1362_42_2025": null, "1347_42_2025": null, "1349_42_2025": null, "1369_42_2025": null, "1353_42_2025": null, "1365_42_2025": null, "1844_42_2025": null, "1381_42_2025": null, "1336_42_2025": null, "1819_42_2025": null, "1842_42_2025": null, "1342_42_2025": null, "1348_42_2025": null, "6479_111_2025": null, "1370_42_2025": null, "1361_42_2025": null, "2202_111_2025": null, "11309_111_2025": null, "6443_111_2025": null, "2190_111_2025": null, "20358_111_2025": null, "5623_111_2025": null, "2192_111_2025": null, "7758_60_2025": null, "7753_60_2025": null, "8783_60_2025": null, "8986_60_2025": null, "7615_60_2025": null, "7712_60_2025": null, "8899_60_2025": null, "1041_714_2025": null, "1039_714_2025": null, "1036_714_2025": null, "7627_60_2025": null, "7520_714_2025": null, "903_183_2025": null, "6781_184_2025": null, "1333_41_2025": null, "6777_183_2025": null, "4250_184_2025": null, "1373_41_2025": null, "1356_41_2025": null, "68_41_2025": null, "1343_41_2025": null, "1351_41_2025": null, "1354_41_2025": null, "1374_41_2025": null, "748_41_2025": null, "37_41_2025": null, "1359_41_2025": null, "53_41_2025": null, "1379_41_2025": null, "1364_41_2025": null, "1350_41_2025": {"scored": 6, "conceded": 10, "total": 16, "qualifies": true}, "1357_41_2025": {"scored": 12, "conceded": 6, "total": 18, "qualifies": true}, "4686_41_2025": {"scored": 6, "conceded": 11, "total": 17, "qualifies": true}, "73_41_2025": {"scored": 3, "conceded": 4, "total": 7, "qualifies": false}, "1368_41_2025": {"scored": 6, "conceded": 6, "total": 12, "qualifies": true}, "1337_41_2025": {"scored": 2, "conceded": 7, "total": 9, "qualifies": false}, "43_41_2025": {"scored": 11, "conceded": 8, "total": 19, "qualifies": true}, "747_41_2025": {"scored": 8, "conceded": 6, "total": 14, "qualifies": true}, "1358_41_2025": {"scored": 10, "conceded": 6, "total": 16, "qualifies": true}, "1823_43_2025": {"scored": 5, "conceded": 5, "total": 10, "qualifies": false}, "61_41_2025": {"scored": 6, "conceded": 8, "total": 14, "qualifies": true}, "8663_43_2025": {"scored": 16, "conceded": 8, "total": 24, "qualifies": true}, "1836_43_2025": {"scored": 11, "conceded": 9, "total": 20, "qualifies": true}, "1341_43_2025": {"scored": 6, "conceded": 6, "total": 12, "qualifies": true}, "4699_43_2025": {"scored": 4, "conceded": 9, "total": 13, "qualifies": true}, "1377_43_2025": {"scored": 6, "conceded": 10, "total": 16, "qualifies": true}, "1339_43_2025": {"scored": 11, "conceded": 5, "total": 16, "qualifies": true}, "1340_43_2025": {"scored": 9, "conceded": 9, "total": 18, "qualifies": true}, "4701_43_2025": {"scored": 7, "conceded": 16, "total": 23, "qualifies": true}, "8656_50_2025": {"scored": 4, "conceded": 10, "total": 14, "qualifies": true}, "7737_50_2025": {"scored": 3, "conceded": 12, "total": 15, "qualifies": true}, "1834_43_2025": {"scored": 8, "conceded": 14, "total": 22, "qualifies": true}, "7706_50_2025": {"scored": 9, "conceded": 7, "total": 16, "qualifies": true}, "7656_50_2025": {"scored": 8, "conceded": 11, "total": 19, "qualifies": true}, "4707_50_2025": {"scored": 5, "conceded": 6, "total": 11, "qualifies": false}, "4692_50_2025": {"scored": 15, "conceded": 6, "total": 21, "qualifies": true}, "10157_50_2025": {"scored": 5, "conceded": 6, "total": 11, "qualifies": false}, "4703_50_2025": {"scored": 4, "conceded": 14, "total": 18, "qualifies": true}, "1839_50_2025": {"scored": 13, "conceded": 6, "total": 19, "qualifies": true}, "7740_50_2025": {"scored": 3, "conceded": 9, "total": 12, "qualifies": true}, "4688_50_2025": {"scored": 9, "conceded": 6, "total": 15, "qualifies": true}, "8655_50_2025": {"scored": 6, "conceded": 8, "total": 14, "qualifies": true}, "1380_50_2025": {"scored": 11, "conceded": 7, "total": 18, "qualifies": true}, "4679_50_2025": {"scored": 4, "conceded": 7, "total": 11, "qualifies": false}, "7746_50_2025": {"scored": 10, "conceded": 4, "total": 14, "qualifies": true}, "4695_50_2025": {"scored": 13, "conceded": 2, "total": 15, "qualifies": true}, "1826_50_2025": {"scored": 7, "conceded": 5, "total": 12, "qualifies": true}, "7434_731_2025": {"scored": 5, "conceded": 10, "total": 15, "qualifies": true}, "6731_731_2025": {"scored": 6, "conceded": 7, "total": 13, "qualifies": true}, "4677_50_2025": {"scored": 4, "conceded": 9, "total": 13, "qualifies": true}, "6759_731_2025": {"scored": 9, "conceded": 7, "total": 16, "qualifies": true}, "6744_731_2025": {"scored": 10, "conceded": 3, "total": 13, "qualifies": true}, "4667_731_2025": {"scored": 6, "conceded": 6, "total": 12, "qualifies": true}, "6756_731_2025": {"scored": 1, "conceded": 12, "total": 13, "qualifies": true}, "4713_58_2025": {"scored": 6, "conceded": 13, "total": 19, "qualifies": true}, "7450_731_2025": {"scored": 5, "conceded": 8, "total": 13, "qualifies": true}, "7439_731_2025": {"scored": 4, "conceded": 18, "total": 22, "qualifies": true}, "7708_58_2025": {"scored": 3, "conceded": 7, "total": 10, "qualifies": false}, "7623_58_2025": {"scored": 4, "conceded": 10, "total": 14, "qualifies": true}, "8654_931_2025": {"scored": 8, "conceded": 4, "total": 12, "qualifies": true}, "7692_931_2025": {"scored": 5, "conceded": 7, "total": 12, "qualifies": true}, "7205_931_2025": {"scored": 5, "conceded": 15, "total": 20, "qualifies": true}, "8737_58_2025": {"scored": 8, "conceded": 2, "total": 10, "qualifies": false}, "4709_931_2025": {"scored": 9, "conceded": 4, "total": 13, "qualifies": true}, "21712_931_2025": {"scored": 8, "conceded": 9, "total": 17, "qualifies": true}, "7705_931_2025": {"scored": 7, "conceded": 11, "total": 18, "qualifies": true}, "9010_931_2025": {"scored": 7, "conceded": 3, "total": 10, "qualifies": false}, "7644_931_2025": {"scored": 10, "conceded": 9, "total": 19, "qualifies": true}, "8812_931_2025": {"scored": 8, "conceded": 2, "total": 10, "qualifies": false}, "4691_59_2025": {"scored": 9, "conceded": 7, "total": 16, "qualifies": true}, "7696_931_2025": {"scored": 4, "conceded": 3, "total": 7, "qualifies": false}, "7757_59_2025": {"scored": 8, "conceded": 7, "total": 15, "qualifies": true}, "4694_59_2025": {"scored": 9, "conceded": 6, "total": 15, "qualifies": true}, "7663_59_2025": {"scored": 5, "conceded": 12, "total": 17, "qualifies": true}, "7693_59_2025": {"scored": 5, "conceded": 6, "total": 11, "qualifies": false}, "7631_59_2025": {"scored": 6, "conceded": 6, "total": 12, "qualifies": true}, "8965_52_2025": {"scored": 6, "conceded": 6, "total": 12, "qualifies": true}, "9011_52_2025": {"scored": 4, "conceded": 6, "total": 10, "qualifies": false}, "8793_52_2025": {"scored": 4, "conceded": 3, "total": 7, "qualifies": false}, "7654_52_2025": {"scored": 8, "conceded": 5, "total": 13, "qualifies": true}, "8950_52_2025": {"scored": 5, "conceded": 9, "total": 14, "qualifies": true}, "8846_933_2025": {"scored": 13, "conceded": 3, "total": 16, "qualifies": true}, "8754_55_2025": {"scored": 8, "conceded": 9, "total": 17, "qualifies": true}, "8658_52_2025": {"scored": 9, "conceded": 3, "total": 12, "qualifies": true}, "7614_933_2025": {"scored": 8, "conceded": 13, "total": 21, "qualifies": true}, "8904_55_2025": {"scored": 3, "conceded": 4, "total": 7, "qualifies": false}, "7691_55_2025": {"scored": 9, "conceded": 8, "total": 17, "qualifies": true}, "6091_167_2026": null, "6114_167_2026": null, "7672_55_2025": {"scored": 10, "conceded": 11, "total": 21, "qualifies": true}, "6085_167_2026": null, "6084_167_2026": null, "6109_167_2026": null, "6108_167_2026": null, "6094_167_2026": null, "2374_269_2026": null, "273_167_2026": null, "2125_250_2026": {"scored": 3, "conceded": 12, "total": 15, "qualifies": true}, "18295_269_2026": null, "1182_250_2026": {"scored": 5, "conceded": 1, "total": 6, "qualifies": false}, "2140_250_2026": {"scored": 2, "conceded": 6, "total": 8, "qualifies": false}, "1185_250_2026": {"scored": 4, "conceded": 2, "total": 6, "qualifies": false}, "1183_250_2026": {"scored": 5, "conceded": 6, "total": 11, "qualifies": false}, "1174_250_2026": {"scored": 9, "conceded": 10, "total": 19, "qualifies": true}, "1176_250_2026": {"scored": 7, "conceded": 2, "total": 9, "qualifies": false}, "1179_250_2026": {"scored": 10, "conceded": 2, "total": 12, "qualifies": true}, "10476_250_2026": {"scored": 4, "conceded": 6, "total": 10, "qualifies": false}, "1157_242_2026": null, "1175_250_2026": {"scored": 6, "conceded": 5, "total": 11, "qualifies": false}, "19034_242_2026": null, "1155_242_2026": null, "1154_242_2026": null, "1158_242_2026": null, "1149_242_2026": null, "1980_242_2026": null, "4108_257_2026": null, "4024_257_2026": null, "1159_242_2026": null, "23215_257_2026": null, "22855_257_2026": null, "4049_257_2026": null, "18912_257_2026": null, "25688_257_2026": null, "4010_257_2026": null, "25486_257_2026": null, "9043_257_2026": null, "23227_257_2026": null, "9037_257_2026": null, "23999_257_2026": null, "3992_257_2026": null, "3999_257_2026": null, "3996_257_2026": null, "9039_257_2026": null, "4009_257_2026": null, "4047_257_2026": null, "9073_257_2026": null, "24028_257_2026": null, "10094_257_2026": null, "27440_257_2026": null, "3990_257_2026": null, "9026_257_2026": null, "25485_257_2026": null, "27439_257_2026": null, "4000_257_2026": null, "9060_257_2026": null, "9022_257_2026": null, "25694_257_2026": null, "27443_257_2026": null, "3995_257_2026": null, "7782_73_2026": null, "18905_257_2026": null, "7865_73_2026": null, "154_73_2026": null, "148_73_2026": null, "129_73_2026": null, "1214_73_2026": null, "1223_73_2026": null, "123_73_2026": null, "149_73_2026": null, "142_73_2026": null, "13975_73_2026": null, "144_73_2026": null, "7772_73_2026": null, "22056_872_2025": {"scored": 7, "conceded": 10, "total": 17, "qualifies": true}, "139_73_2026": null, "12916_607_2026": {"scored": 12, "conceded": 5, "total": 17, "qualifies": true}, "15918_872_2025": {"scored": 7, "conceded": 4, "total": 11, "qualifies": false}, "7876_607_2026": {"scored": 1, "conceded": 14, "total": 15, "qualifies": true}, "7840_607_2026": {"scored": 13, "conceded": 4, "total": 17, "qualifies": true}, "12213_568_2025": {"scored": 10, "conceded": 12, "total": 22, "qualifies": true}, "21230_607_2026": {"scored": 7, "conceded": 16, "total": 23, "qualifies": true}, "12214_568_2025": {"scored": 2, "conceded": 19, "total": 21, "qualifies": true}, "12219_568_2025": {"scored": 8, "conceded": 6, "total": 14, "qualifies": true}, "822_16_2026": null, "10966_568_2025": {"scored": 9, "conceded": 8, "total": 17, "qualifies": true}, "2295_16_2026": null, "1616_16_2026": null, "2282_16_2026": null, "9568_16_2026": null, "27383_1214_2026": {"scored": 9, "conceded": 8, "total": 17, "qualifies": true}, "8141_1214_2026": {"scored": 7, "conceded": 11, "total": 18, "qualifies": true}, "9569_16_2026": null, "26722_1214_2026": {"scored": 8, "conceded": 4, "total": 12, "qualifies": true}, "27382_1214_2026": {"scored": 5, "conceded": 6, "total": 11, "qualifies": false}, "21580_765_2026": {"scored": 5, "conceded": 41, "total": 46, "qualifies": true}, "21576_765_2026": {"scored": 27, "conceded": 1, "total": 28, "qualifies": true}, "16192_765_2026": {"scored": 2, "conceded": 30, "total": 32, "qualifies": true}, "24582_728_2025": {"scored": 1, "conceded": 18, "total": 19, "qualifies": true}, "22754_765_2026": {"scored": 17, "conceded": 5, "total": 22, "qualifies": true}, "22191_728_2025": {"scored": 10, "conceded": 10, "total": 20, "qualifies": true}, "10899_728_2025": {"scored": 17, "conceded": 4, "total": 21, "qualifies": true}, "19903_728_2025": {"scored": 19, "conceded": 8, "total": 27, "qualifies": true}, "24584_728_2025": {"scored": 8, "conceded": 6, "total": 14, "qualifies": true}, "17659_728_2025": {"scored": 11, "conceded": 9, "total": 20, "qualifies": true}, "22192_728_2025": {"scored": 20, "conceded": 3, "total": 23, "qualifies": true}, "15970_728_2025": {"scored": 1, "conceded": 29, "total": 30, "qualifies": true}, "291_98_2026": {"scored": 5, "conceded": 4, "total": 9, "qualifies": false}, "316_98_2026": {"scored": 2, "conceded": 12, "total": 14, "qualifies": true}, "310_98_2026": {"scored": 5, "conceded": 5, "total": 10, "qualifies": false}, "301_98_2026": {"scored": 4, "conceded": 6, "total": 10, "qualifies": false}, "283_98_2026": {"scored": 5, "conceded": 4, "total": 9, "qualifies": false}, "305_98_2026": {"scored": 6, "conceded": 8, "total": 14, "qualifies": true}, "292_98_2026": {"scored": 7, "conceded": 5, "total": 12, "qualifies": true}, "288_98_2026": {"scored": 7, "conceded": 8, "total": 15, "qualifies": true}, "296_98_2026": {"scored": 5, "conceded": 8, "total": 13, "qualifies": true}, "306_98_2026": {"scored": 7, "conceded": 8, "total": 15, "qualifies": true}, "282_98_2026": {"scored": 9, "conceded": 5, "total": 14, "qualifies": true}, "294_98_2026": {"scored": 8, "conceded": 8, "total": 16, "qualifies": true}, "289_98_2026": {"scored": 8, "conceded": 3, "total": 11, "qualifies": false}, "285_98_2026": {"scored": 7, "conceded": 6, "total": 13, "qualifies": true}, "293_98_2026": {"scored": 7, "conceded": 7, "total": 14, "qualifies": true}, "303_98_2026": {"scored": 10, "conceded": 7, "total": 17, "qualifies": true}, "302_98_2026": {"scored": 6, "conceded": 5, "total": 11, "qualifies": false}, "287_98_2026": {"scored": 7, "conceded": 5, "total": 12, "qualifies": true}, "290_98_2026": {"scored": 9, "conceded": 2, "total": 11, "qualifies": false}, "666_419_2025": {"scored": 3, "conceded": 2, "total": 5, "qualifies": false}, "281_98_2026": {"scored": 4, "conceded": 7, "total": 11, "qualifies": false}, "25318_418_2025": {"scored": 14, "conceded": 4, "total": 18, "qualifies": true}, "11238_419_2025": {"scored": 5, "conceded": 8, "total": 13, "qualifies": true}, "22788_418_2025": {"scored": 7, "conceded": 3, "total": 10, "qualifies": false}, "5576_418_2025": {"scored": 8, "conceded": 5, "total": 13, "qualifies": true}, "4199_418_2025": {"scored": 5, "conceded": 2, "total": 7, "qualifies": false}, "5573_418_2025": {"scored": 5, "conceded": 3, "total": 8, "qualifies": false}, "5492_418_2025": {"scored": 4, "conceded": 6, "total": 10, "qualifies": false}, "12202_567_2025": {"scored": 4, "conceded": 9, "total": 13, "qualifies": true}, "22175_567_2025": {"scored": 7, "conceded": 7, "total": 14, "qualifies": true}, "3669_341_2026": null, "24353_567_2025": {"scored": 7, "conceded": 7, "total": 14, "qualifies": true}, "5370_567_2025": {"scored": 9, "conceded": 0, "total": 9, "qualifies": false}, "3674_341_2026": null, "5396_1174_2025": null, "5394_1174_2025": null, "2772_898_2025": null, "5389_1174_2025": null, "21735_1174_2025": null, "20430_898_2025": null, "2769_898_2025": null, "6582_898_2025": null, "2789_898_2025": null, "17910_898_2025": null, "2780_898_2025": null, "10086_898_2025": null, "2472_276_2025": {"scored": 8, "conceded": 7, "total": 15, "qualifies": true}, "3749_356_2025": {"scored": 6, "conceded": 7, "total": 13, "qualifies": true}, "3746_356_2025": {"scored": 3, "conceded": 12, "total": 15, "qualifies": true}, "22231_276_2025": {"scored": 7, "conceded": 4, "total": 11, "qualifies": false}, "3743_356_2025": {"scored": 5, "conceded": 6, "total": 11, "qualifies": false}, "21530_356_2025": {"scored": 7, "conceded": 7, "total": 14, "qualifies": true}, "3738_356_2025": {"scored": 3, "conceded": 2, "total": 5, "qualifies": false}, "3739_356_2025": {"scored": 8, "conceded": 6, "total": 14, "qualifies": true}, "3737_356_2025": {"scored": 12, "conceded": 4, "total": 16, "qualifies": true}, "2258_356_2025": {"scored": 5, "conceded": 6, "total": 11, "qualifies": false}, "3750_356_2025": {"scored": 5, "conceded": 8, "total": 13, "qualifies": true}, "26200_400_2025": {"scored": 2, "conceded": 7, "total": 9, "qualifies": false}, "7455_400_2025": {"scored": 5, "conceded": 6, "total": 11, "qualifies": false}, "3751_356_2025": {"scored": 9, "conceded": 6, "total": 15, "qualifies": true}, "5214_400_2025": {"scored": 4, "conceded": 10, "total": 14, "qualifies": true}, "5210_400_2025": {"scored": 2, "conceded": 8, "total": 10, "qualifies": false}, "21875_400_2025": {"scored": 5, "conceded": 3, "total": 8, "qualifies": false}, "5205_400_2025": {"scored": 6, "conceded": 8, "total": 14, "qualifies": true}, "5207_400_2025": {"scored": 3, "conceded": 7, "total": 10, "qualifies": false}, "5200_400_2025": {"scored": 5, "conceded": 5, "total": 10, "qualifies": false}, "5199_400_2025": {"scored": 4, "conceded": 8, "total": 12, "qualifies": true}, "5514_400_2025": {"scored": 5, "conceded": 5, "total": 10, "qualifies": false}, "5209_400_2025": {"scored": 3, "conceded": 4, "total": 7, "qualifies": false}, "5206_400_2025": {"scored": 5, "conceded": 4, "total": 9, "qualifies": false}, "5212_400_2025": {"scored": 4, "conceded": 4, "total": 8, "qualifies": false}, "5201_400_2025": {"scored": 9, "conceded": 2, "total": 11, "qualifies": false}, "5215_400_2025": {"scored": 6, "conceded": 4, "total": 10, "qualifies": false}, "5511_400_2025": {"scored": 8, "conceded": 6, "total": 14, "qualifies": true}, "5211_400_2025": {"scored": 13, "conceded": 5, "total": 18, "qualifies": true}, "5213_400_2025": {"scored": 5, "conceded": 3, "total": 8, "qualifies": false}, "4453_1199_2025": null, "14220_175_2025": {"scored": 3, "conceded": 12, "total": 15, "qualifies": true}, "26846_175_2025": {"scored": 19, "conceded": 9, "total": 28, "qualifies": true}, "20392_1199_2025": null, "21835_175_2025": {"scored": 14, "conceded": 7, "total": 21, "qualifies": true}, "8510_175_2025": {"scored": 7, "conceded": 9, "total": 16, "qualifies": true}, "26249_175_2025": {"scored": 3, "conceded": 13, "total": 16, "qualifies": true}, "8514_175_2025": {"scored": 12, "conceded": 3, "total": 15, "qualifies": true}, "8509_175_2025": {"scored": 5, "conceded": 12, "total": 17, "qualifies": true}, "8551_175_2025": {"scored": 11, "conceded": 4, "total": 15, "qualifies": true}, "17310_175_2025": {"scored": 4, "conceded": 12, "total": 16, "qualifies": true}, "1422_175_2025": {"scored": 16, "conceded": 2, "total": 18, "qualifies": true}, "14222_175_2025": {"scored": 15, "conceded": 5, "total": 20, "qualifies": true}, "17309_175_2025": {"scored": 7, "conceded": 7, "total": 14, "qualifies": true}, "19831_178_2025": {"scored": 2, "conceded": 10, "total": 12, "qualifies": true}, "27274_401_2026": null, "8548_178_2025": {"scored": 6, "conceded": 7, "total": 13, "qualifies": true}, "5220_401_2026": null, "5224_401_2026": null, "27275_401_2026": null, "25734_401_2026": null, "5229_401_2026": null, "5230_401_2026": null, "5231_401_2026": null, "5226_401_2026": null, "5232_401_2026": null, "21055_401_2026": null, "17740_311_2025": {"scored": 3, "conceded": 6, "total": 9, "qualifies": false}, "5218_401_2026": null, "3319_311_2025": {"scored": 4, "conceded": 7, "total": 11, "qualifies": false}, "3321_311_2025": {"scored": 4, "conceded": 9, "total": 13, "qualifies": true}, "577_311_2025": {"scored": 6, "conceded": 5, "total": 11, "qualifies": false}, "3324_311_2025": {"scored": 0, "conceded": 3, "total": 3, "qualifies": false}, "2256_311_2025": {"scored": 12, "conceded": 4, "total": 16, "qualifies": true}, "3332_311_2025": {"scored": 3, "conceded": 12, "total": 15, "qualifies": true}, "3334_311_2025": {"scored": 14, "conceded": 5, "total": 19, "qualifies": true}, "3322_311_2025": {"scored": 7, "conceded": 8, "total": 15, "qualifies": true}, "605_311_2025": {"scored": 11, "conceded": 3, "total": 14, "qualifies": true}, "3330_311_2025": {"scored": 5, "conceded": 2, "total": 7, "qualifies": false}, "3331_311_2025": {"scored": 4, "conceded": 9, "total": 13, "qualifies": true}, "25526_289_2025": {"scored": 3, "conceded": 5, "total": 8, "qualifies": false}, "18177_427_2025": {"scored": 7, "conceded": 4, "total": 11, "qualifies": false}, "22235_289_2025": {"scored": 6, "conceded": 5, "total": 11, "qualifies": false}, "9448_427_2025": {"scored": 6, "conceded": 4, "total": 10, "qualifies": false}, "9472_428_2025": {"scored": 9, "conceded": 7, "total": 16, "qualifies": true}, "3405_319_2025": {"scored": 2, "conceded": 11, "total": 13, "qualifies": true}, "3413_319_2025": {"scored": 11, "conceded": 6, "total": 17, "qualifies": true}, "17133_428_2025": {"scored": 7, "conceded": 3, "total": 10, "qualifies": false}, "14126_319_2025": {"scored": 9, "conceded": 3, "total": 12, "qualifies": true}, "3409_319_2025": {"scored": 1, "conceded": 8, "total": 9, "qualifies": false}, "3414_319_2025": {"scored": 6, "conceded": 5, "total": 11, "qualifies": false}, "3401_319_2025": {"scored": 9, "conceded": 3, "total": 12, "qualifies": true}, "3419_319_2025": {"scored": 4, "conceded": 5, "total": 9, "qualifies": false}, "20024_319_2025": {"scored": 4, "conceded": 15, "total": 19, "qualifies": true}, "3398_319_2025": {"scored": 6, "conceded": 7, "total": 13, "qualifies": true}, "3423_319_2025": {"scored": 10, "conceded": 5, "total": 15, "qualifies": true}, "3420_319_2025": {"scored": 3, "conceded": 4, "total": 7, "qualifies": false}, "3429_319_2025": {"scored": 8, "conceded": 3, "total": 11, "qualifies": false}, "3428_319_2025": {"scored": 6, "conceded": 5, "total": 11, "qualifies": false}, "3404_319_2025": {"scored": 7, "conceded": 8, "total": 15, "qualifies": true}, "4346_756_2025": null, "6405_319_2025": {"scored": 8, "conceded": 4, "total": 12, "qualifies": true}, "22127_319_2025": {"scored": 5, "conceded": 7, "total": 12, "qualifies": true}, "609_756_2025": null, "2523_278_2025": {"scored": 20, "conceded": 2, "total": 22, "qualifies": true}, "8020_636_2026": null, "2500_278_2025": {"scored": 3, "conceded": 11, "total": 14, "qualifies": true}, "6950_109_2025": {"scored": 5, "conceded": 7, "total": 12, "qualifies": true}, "13158_636_2026": null, "3492_109_2025": {"scored": 9, "conceded": 3, "total": 12, "qualifies": true}, "3486_109_2025": {"scored": 2, "conceded": 13, "total": 15, "qualifies": true}, "12801_109_2025": {"scored": 3, "conceded": 11, "total": 14, "qualifies": true}, "16255_109_2025": {"scored": 6, "conceded": 4, "total": 10, "qualifies": false}, "6958_109_2025": {"scored": 5, "conceded": 9, "total": 14, "qualifies": true}, "3496_109_2025": {"scored": 7, "conceded": 6, "total": 13, "qualifies": true}, "3482_109_2025": {"scored": 5, "conceded": 4, "total": 9, "qualifies": false}, "12902_109_2025": {"scored": 9, "conceded": 9, "total": 18, "qualifies": true}, "17397_109_2025": {"scored": 8, "conceded": 9, "total": 17, "qualifies": true}, "6961_109_2025": {"scored": 12, "conceded": 5, "total": 17, "qualifies": true}, "4212_369_2026": null, "342_109_2025": {"scored": 4, "conceded": 16, "total": 20, "qualifies": true}, "16381_369_2026": null, "4216_369_2026": null, "4210_369_2026": null, "4221_369_2026": null, "9786_449_2025": {"scored": 5, "conceded": 6, "total": 11, "qualifies": false}, "26536_449_2025": {"scored": 5, "conceded": 11, "total": 16, "qualifies": true}, "4219_369_2026": null, "17599_449_2025": {"scored": 3, "conceded": 3, "total": 6, "qualifies": false}, "17598_449_2025": {"scored": 9, "conceded": 4, "total": 13, "qualifies": true}, "27432_569_2026": null, "27550_569_2026": null, "8026_569_2026": null, "21167_569_2026": null, "12238_569_2026": null, "217_3_2025": {"scored": 3, "conceded": 3, "total": 6, "qualifies": false}, "21953_333_2025": {"scored": 6, "conceded": 4, "total": 10, "qualifies": false}, "12236_569_2026": null, "651_3_2025": {"scored": 6, "conceded": 7, "total": 13, "qualifies": true}, "6496_333_2025": {"scored": 11, "conceded": 5, "total": 16, "qualifies": true}, "9732_446_2025": {"scored": 2, "conceded": 3, "total": 5, "qualifies": false}, "21103_243_2026": null, "14014_82_2025": {"scored": 12, "conceded": 7, "total": 19, "qualifies": true}, "26546_446_2025": {"scored": 7, "conceded": 11, "total": 18, "qualifies": true}, "19042_243_2026": null, "1858_82_2025": {"scored": 8, "conceded": 4, "total": 12, "qualifies": true}, "16849_82_2025": {"scored": 5, "conceded": 17, "total": 22, "qualifies": true}, "16274_783_2025": {"scored": 2, "conceded": 1, "total": 3, "qualifies": false}, "1863_82_2025": {"scored": 9, "conceded": 8, "total": 17, "qualifies": true}, "16265_783_2025": {"scored": 2, "conceded": 11, "total": 13, "qualifies": true}, "24612_878_2025": {"scored": 9, "conceded": 2, "total": 11, "qualifies": false}, "1028_220_2025": null, "5268_878_2025": {"scored": 5, "conceded": 7, "total": 12, "qualifies": true}, "759_105_2026": null, "1026_220_2025": null, "14717_939_2025": {"scored": 16, "conceded": 6, "total": 22, "qualifies": true}, "757_105_2026": null, "12822_753_2025": {"scored": 6, "conceded": 3, "total": 9, "qualifies": false}, "12832_939_2025": null, "9356_754_2025": null, "26167_753_2025": null, "16119_754_2025": null, "12858_754_2025": null, "14722_754_2025": null, "12874_754_2025": null, "9350_755_2025": null, "9351_754_2025": null, "12839_747_2025": null, "1643_755_2025": null, "9372_747_2025": null, "26186_747_2025": null, "14826_747_2025": null, "16088_747_2025": null, "24431_747_2025": null, "20873_747_2025": null, "3108_67_2025": null, "14704_747_2025": null, "3097_67_2025": null, "1303_67_2025": null, "9275_67_2025": null, "10166_67_2025": null, "24656_451_2025": null, "3224_67_2025": null, "23572_1062_2026": null, "9820_451_2025": null, "23581_1062_2026": null, "23573_1062_2026": null, "22953_1062_2026": null, "7786_1062_2026": null, "18466_1062_2026": null, "22947_1062_2026": null, "10022_1062_2026": null, "22950_1062_2026": null, "23569_1062_2026": null, "22949_1062_2026": null, "10028_1062_2026": null, "10036_1062_2026": null, "10031_1062_2026": null, "23576_1062_2026": null, "7825_1063_2026": null, "22955_1062_2026": null, "22822_1063_2026": null, "18363_1063_2026": null, "9127_1063_2026": null, "22960_1063_2026": null, "1207_1063_2026": null, "1210_1063_2026": null, "12844_751_2025": null, "9128_1063_2026": null, "14500_744_2025": null, "1322_751_2025": null, "12782_748_2025": null, "24434_744_2025": null, "17143_748_2025": null, "13941_748_2025": null, "1644_749_2025": null, "14787_748_2025": null, "18162_601_2025": null, "4263_749_2025": null, "6650_601_2025": null, "12712_601_2025": null, "12721_601_2025": null, "12715_601_2025": null, "1853_44_2025": null, "12720_601_2025": null, "1856_44_2025": null, "1857_44_2025": null, "6614_600_2025": null, "4898_44_2025": null, "12708_600_2025": null, "12701_600_2025": {"scored": 10, "conceded": 10, "total": 20, "qualifies": true}, "10589_600_2025": {"scored": 7, "conceded": 8, "total": 15, "qualifies": true}, "10593_600_2025": {"scored": 11, "conceded": 10, "total": 21, "qualifies": true}, "16337_599_2025": {"scored": 6, "conceded": 7, "total": 13, "qualifies": true}, "12707_600_2025": {"scored": 6, "conceded": 9, "total": 15, "qualifies": true}, "17413_599_2025": {"scored": 6, "conceded": 8, "total": 14, "qualifies": true}, "16332_599_2025": {"scored": 10, "conceded": 14, "total": 24, "qualifies": true}, "12695_599_2025": {"scored": 5, "conceded": 9, "total": 14, "qualifies": true}, "6628_599_2025": {"scored": 7, "conceded": 6, "total": 13, "qualifies": true}, "12692_599_2025": {"scored": 10, "conceded": 10, "total": 20, "qualifies": true}, "6630_599_2025": {"scored": 9, "conceded": 7, "total": 16, "qualifies": true}, "12694_599_2025": {"scored": 5, "conceded": 12, "total": 17, "qualifies": true}, "16339_599_2025": {"scored": 5, "conceded": 6, "total": 11, "qualifies": false}, "16316_599_2025": {"scored": 15, "conceded": 6, "total": 21, "qualifies": true}, "24614_453_2025": {"scored": 2, "conceded": 9, "total": 11, "qualifies": false}, "9845_453_2025": {"scored": 2, "conceded": 6, "total": 8, "qualifies": false}, "26553_453_2025": {"scored": 4, "conceded": 7, "total": 11, "qualifies": false}, "9857_453_2025": {"scored": 7, "conceded": 9, "total": 16, "qualifies": true}, "9406_453_2025": {"scored": 7, "conceded": 7, "total": 14, "qualifies": true}, "2929_504_2026": null, "10509_504_2026": null, "9849_453_2025": {"scored": 5, "conceded": 9, "total": 14, "qualifies": true}, "2932_504_2026": null, "2938_504_2026": null, "17000_1039_2025": null, "7193_1039_2025": null, "16847_299_2026": {"scored": 5, "conceded": 13, "total": 18, "qualifies": true}, "9585_1039_2025": null, "9367_1039_2025": null, "2807_299_2026": {"scored": 6, "conceded": 4, "total": 10, "qualifies": false}, "18806_299_2026": {"scored": 4, "conceded": 6, "total": 10, "qualifies": false}, "2808_299_2026": {"scored": 2, "conceded": 6, "total": 8, "qualifies": false}, "2827_299_2026": {"scored": 5, "conceded": 4, "total": 9, "qualifies": false}, "2813_299_2026": {"scored": 5, "conceded": 1, "total": 6, "qualifies": false}, "2815_299_2026": {"scored": 4, "conceded": 7, "total": 11, "qualifies": false}, "2840_299_2026": {"scored": 13, "conceded": 6, "total": 19, "qualifies": true}, "2818_299_2026": {"scored": 7, "conceded": 5, "total": 12, "qualifies": true}, "2806_299_2026": {"scored": 3, "conceded": 7, "total": 10, "qualifies": false}, "2825_299_2026": {"scored": 8, "conceded": 6, "total": 14, "qualifies": true}, "2810_299_2026": {"scored": 7, "conceded": 1, "total": 8, "qualifies": false}, "2814_299_2026": {"scored": 9, "conceded": 9, "total": 18, "qualifies": true}, "2811_299_2026": {"scored": 6, "conceded": 9, "total": 15, "qualifies": true}, "1710_891_2025": {"scored": 8, "conceded": 4, "total": 12, "qualifies": true}, "5352_408_2025": {"scored": 14, "conceded": 2, "total": 16, "qualifies": true}, "2266_408_2025": {"scored": 5, "conceded": 5, "total": 10, "qualifies": false}, "5302_729_2025": {"scored": 7, "conceded": 3, "total": 10, "qualifies": false}, "804_891_2025": {"scored": 5, "conceded": 3, "total": 8, "qualifies": false}, "2260_729_2025": {"scored": 11, "conceded": 2, "total": 13, "qualifies": true}, "2249_729_2025": {"scored": 5, "conceded": 2, "total": 7, "qualifies": false}, "6729_730_2025": {"scored": 8, "conceded": 5, "total": 13, "qualifies": true}, "5308_729_2025": null, "7445_730_2025": {"scored": 11, "conceded": 12, "total": 23, "qualifies": true}, "7451_730_2025": {"scored": 10, "conceded": 8, "total": 18, "qualifies": true}, "7447_730_2025": {"scored": 1, "conceded": 12, "total": 13, "qualifies": true}, "6769_730_2025": {"scored": 7, "conceded": 4, "total": 11, "qualifies": false}, "6760_730_2025": {"scored": 18, "conceded": 3, "total": 21, "qualifies": true}, "7452_730_2025": {"scored": 8, "conceded": 5, "total": 13, "qualifies": true}, "7432_730_2025": {"scored": 9, "conceded": 6, "total": 15, "qualifies": true}, "7441_730_2025": {"scored": 9, "conceded": 9, "total": 18, "qualifies": true}, "6768_730_2025": {"scored": 11, "conceded": 4, "total": 15, "qualifies": true}, "12566_591_2026": {"scored": 5, "conceded": 16, "total": 21, "qualifies": true}, "12562_591_2026": {"scored": 9, "conceded": 12, "total": 21, "qualifies": true}, "25276_591_2026": {"scored": 8, "conceded": 18, "total": 26, "qualifies": true}, "20974_591_2026": {"scored": 12, "conceded": 6, "total": 18, "qualifies": true}, "12559_591_2026": {"scored": 11, "conceded": 1, "total": 12, "qualifies": true}, "12567_591_2026": {"scored": 15, "conceded": 3, "total": 18, "qualifies": true}, "12564_591_2026": {"scored": 7, "conceded": 10, "total": 17, "qualifies": true}, "8005_591_2026": {"scored": 8, "conceded": 15, "total": 23, "qualifies": true}, "3645_339_2025": {"scored": 7, "conceded": 4, "total": 11, "qualifies": false}, "4310_370_2025": {"scored": 2, "conceded": 7, "total": 9, "qualifies": false}, "3636_339_2025": {"scored": 1, "conceded": 8, "total": 9, "qualifies": false}, "4304_370_2025": {"scored": 5, "conceded": 6, "total": 11, "qualifies": false}, "4299_370_2025": {"scored": 9, "conceded": 4, "total": 13, "qualifies": true}, "4302_370_2025": {"scored": 12, "conceded": 3, "total": 15, "qualifies": true}, "22157_370_2025": {"scored": 8, "conceded": 9, "total": 17, "qualifies": true}, "24530_370_2025": {"scored": 4, "conceded": 8, "total": 12, "qualifies": true}, "26156_370_2025": {"scored": 5, "conceded": 13, "total": 18, "qualifies": true}, "26154_370_2025": {"scored": 5, "conceded": 6, "total": 11, "qualifies": false}, "4306_370_2025": {"scored": 11, "conceded": 4, "total": 15, "qualifies": true}, "26155_370_2025": {"scored": 3, "conceded": 7, "total": 10, "qualifies": false}, "19763_370_2025": {"scored": 10, "conceded": 5, "total": 15, "qualifies": true}, "10018_476_2026": {"scored": 9, "conceded": 7, "total": 16, "qualifies": true}, "4303_370_2025": {"scored": 5, "conceded": 7, "total": 12, "qualifies": true}, "2230_476_2026": {"scored": 9, "conceded": 9, "total": 18, "qualifies": true}, "7779_476_2026": {"scored": 8, "conceded": 10, "total": 18, "qualifies": true}, "15622_476_2026": {"scored": 10, "conceded": 5, "total": 15, "qualifies": true}, "7870_476_2026": {"scored": 7, "conceded": 5, "total": 12, "qualifies": true}, "10019_476_2026": {"scored": 10, "conceded": 3, "total": 13, "qualifies": true}, "1228_520_2026": {"scored": 9, "conceded": 5, "total": 14, "qualifies": true}, "2220_520_2026": {"scored": 6, "conceded": 6, "total": 12, "qualifies": true}, "13094_621_2026": {"scored": 8, "conceded": 2, "total": 10, "qualifies": false}, "2217_623_2026": {"scored": 5, "conceded": 4, "total": 9, "qualifies": false}, "25417_621_2026": {"scored": 8, "conceded": 2, "total": 10, "qualifies": false}, "1206_623_2026": {"scored": 8, "conceded": 2, "total": 10, "qualifies": false}, "18365_623_2026": {"scored": 9, "conceded": 5, "total": 14, "qualifies": true}, "10675_615_2026": {"scored": 15, "conceded": 1, "total": 16, "qualifies": true}, "12946_615_2026": {"scored": 11, "conceded": 1, "total": 12, "qualifies": true}, "27285_623_2026": {"scored": 11, "conceded": 15, "total": 26, "qualifies": true}, "7877_615_2026": {"scored": 7, "conceded": 4, "total": 11, "qualifies": false}, "12944_615_2026": {"scored": 8, "conceded": 6, "total": 14, "qualifies": true}, "8571_424_2025": null, "5557_813_2026": {"scored": 3, "conceded": 5, "total": 8, "qualifies": false}, "15285_424_2025": null, "27457_813_2026": {"scored": 6, "conceded": 3, "total": 9, "qualifies": false}, "814_163_2025": {"scored": 7, "conceded": 9, "total": 16, "qualifies": true}, "26343_163_2025": {"scored": 6, "conceded": 2, "total": 8, "qualifies": false}, "19414_243_2026": null, "754_616_2026": {"scored": 13, "conceded": 7, "total": 20, "qualifies": true}, "2233_616_2026": {"scored": 8, "conceded": 2, "total": 10, "qualifies": false}, "27053_424_2025": {"scored": 5, "conceded": 0, "total": 5, "qualifies": false}, "24107_424_2025": {"scored": 2, "conceded": 8, "total": 10, "qualifies": false}, "8575_424_2025": {"scored": 4, "conceded": 5, "total": 9, "qualifies": false}}}