{
  "generated_at": "2026-07-04T19:30:04.149142+00:00",
  "total_markets": 117,
  "markets": [
    {
      "market_id": "1.259718018",
      "event_name": "CEAC/Araruama v Cabofriense",
      "start_time": "2026-07-04T17:45:00.000Z",
      "runner_id": 41849516,
      "best_back_price": 5.9,
      "best_back_size": 20.0
    },
    {
      "market_id": "1.259719487",
      "event_name": "Resende v Americano",
      "start_time": "2026-07-04T17:45:00.000Z",
      "runner_id": 2763329,
      "best_back_price": 18.0,
      "best_back_size": 23.0
    },
    {
      "market_id": "1.259718123",
      "event_name": "Sao Goncalo EC RJ v Audax Rio",
      "start_time": "2026-07-04T17:45:00.000Z",
      "runner_id": 11730391,
      "best_back_price": 4.0,
      "best_back_size": 109.19
    },
    {
      "market_id": "1.259719508",
      "event_name": "Olaria v Bonsucesso",
      "start_time": "2026-07-04T17:45:00.000Z",
      "runner_id": 1040275,
      "best_back_price": 23.0,
      "best_back_size": 15.74
    },
    {
      "market_id": "1.259718144",
      "event_name": "America RJ v Serrano FC (RJ)",
      "start_time": "2026-07-04T17:45:00.000Z",
      "runner_id": 4435485,
      "best_back_price": null,
      "best_back_size": null
    },
    {
      "market_id": "1.259718102",
      "event_name": "Marica v Perolas Negras",
      "start_time": "2026-07-04T17:45:00.000Z",
      "runner_id": 79308787,
      "best_back_price": 1.19,
      "best_back_size": 120.35
    },
    {
      "market_id": "1.259657052",
      "event_name": "CA Colegiales v Club Gimnasia y Tiro",
      "start_time": "2026-07-04T18:00:00.000Z",
      "runner_id": 7670892,
      "best_back_price": 3.9,
      "best_back_size": 14.0
    },
    {
      "market_id": "1.259662176",
      "event_name": "Deportivo Merlo v Villa Dalmine",
      "start_time": "2026-07-04T18:00:00.000Z",
      "runner_id": 5181458,
      "best_back_price": 3.35,
      "best_back_size": 28.92
    },
    {
      "market_id": "1.259661588",
      "event_name": "Deportivo Armenio v Brown de Adrogue",
      "start_time": "2026-07-04T18:30:00.000Z",
      "runner_id": 7108497,
      "best_back_price": 2.58,
      "best_back_size": 14.0
    },
    {
      "market_id": "1.259658760",
      "event_name": "CA Temperley v Tristan Suarez",
      "start_time": "2026-07-04T18:30:00.000Z",
      "runner_id": 8742769,
      "best_back_price": 1.24,
      "best_back_size": 255.75
    },
    {
      "market_id": "1.259645155",
      "event_name": "Longford v UCD",
      "start_time": "2026-07-04T18:30:00.000Z",
      "runner_id": 184330,
      "best_back_price": 20.0,
      "best_back_size": 32.0
    },
    {
      "market_id": "1.259658788",
      "event_name": "Almirante Brown v Los Andes",
      "start_time": "2026-07-04T18:30:00.000Z",
      "runner_id": 5359221,
      "best_back_price": 3.6,
      "best_back_size": 88.59
    },
    {
      "market_id": "1.259658774",
      "event_name": "Nueva Chicago v CA Guemes",
      "start_time": "2026-07-04T18:30:00.000Z",
      "runner_id": 194504,
      "best_back_price": 1.31,
      "best_back_size": 111.56
    },
    {
      "market_id": "1.259658732",
      "event_name": "Almagro BA v Atletico Rafaela",
      "start_time": "2026-07-04T18:30:00.000Z",
      "runner_id": 5499132,
      "best_back_price": 2.96,
      "best_back_size": 29.0
    },
    {
      "market_id": "1.259658802",
      "event_name": "Defensores de Belgrano v Deportivo Moron",
      "start_time": "2026-07-04T18:30:00.000Z",
      "runner_id": 5643646,
      "best_back_price": 12.0,
      "best_back_size": 17.48
    },
    {
      "market_id": "1.259731663",
      "event_name": "Union San Felipe v Union La Calera",
      "start_time": "2026-07-04T19:00:00.000Z",
      "runner_id": 4966011,
      "best_back_price": 3.6,
      "best_back_size": 60.4
    },
    {
      "market_id": "1.259658746",
      "event_name": "Ciudad de Bolivar v Godoy Cruz",
      "start_time": "2026-07-04T19:00:00.000Z",
      "runner_id": 27910101,
      "best_back_price": 1.65,
      "best_back_size": 187.59
    },
    {
      "market_id": "1.259688384",
      "event_name": "Novorizontino v Atletico GO",
      "start_time": "2026-07-04T19:00:00.000Z",
      "runner_id": 9173038,
      "best_back_price": 2.28,
      "best_back_size": 44.0
    },
    {
      "market_id": "1.259688405",
      "event_name": "Londrina v CRB",
      "start_time": "2026-07-04T19:00:00.000Z",
      "runner_id": 4525642,
      "best_back_price": 1.73,
      "best_back_size": 50.51
    },
    {
      "market_id": "1.259689737",
      "event_name": "Libertad FC v CD Leones del Norte",
      "start_time": "2026-07-04T19:00:00.000Z",
      "runner_id": 44232344,
      "best_back_price": 1.09,
      "best_back_size": 87.06
    },
    {
      "market_id": "1.259688363",
      "event_name": "Criciuma v Sport Recife",
      "start_time": "2026-07-04T19:00:00.000Z",
      "runner_id": 356589,
      "best_back_price": 1.99,
      "best_back_size": 33.0
    },
    {
      "market_id": "1.259660270",
      "event_name": "Magallanes v Palestino",
      "start_time": "2026-07-04T19:00:00.000Z",
      "runner_id": 5678438,
      "best_back_price": 1.68,
      "best_back_size": 35.0
    },
    {
      "market_id": "1.259740355",
      "event_name": "Argentino de Quilmes v Talleres (RE)",
      "start_time": "2026-07-04T20:00:00.000Z",
      "runner_id": 9534165,
      "best_back_price": 1.01,
      "best_back_size": 13.0
    },
    {
      "market_id": "1.259662734",
      "event_name": "San Luis v Everton De Vina",
      "start_time": "2026-07-04T20:00:00.000Z",
      "runner_id": 328915,
      "best_back_price": 3.45,
      "best_back_size": 81.0
    },
    {
      "market_id": "1.259634374",
      "event_name": "Paraguay v France",
      "start_time": "2026-07-04T21:00:00.000Z",
      "runner_id": 55211,
      "best_back_price": 22.0,
      "best_back_size": 13.58
    },
    {
      "market_id": "1.259661584",
      "event_name": "Quilmes v CA Atlanta",
      "start_time": "2026-07-04T21:00:00.000Z",
      "runner_id": 476270,
      "best_back_price": 2.46,
      "best_back_size": 26.79
    },
    {
      "market_id": "1.259663349",
      "event_name": "Deportes Iquique v Coquimbo Unido",
      "start_time": "2026-07-04T22:00:00.000Z",
      "runner_id": 5271441,
      "best_back_price": 4.0,
      "best_back_size": 98.0
    },
    {
      "market_id": "1.259691022",
      "event_name": "Goias v Ceara SC Fortaleza",
      "start_time": "2026-07-04T23:00:00.000Z",
      "runner_id": 198131,
      "best_back_price": 2.22,
      "best_back_size": 65.84
    },
    {
      "market_id": "1.259731374",
      "event_name": "Cancun FC v Pumas UNAM",
      "start_time": "2026-07-05T00:00:00.000Z",
      "runner_id": 35917994,
      "best_back_price": 5.3,
      "best_back_size": 20.0
    },
    {
      "market_id": "1.259689881",
      "event_name": "Barcelona (Ecu) v Deportivo Cuenca",
      "start_time": "2026-07-05T00:00:00.000Z",
      "runner_id": 13749040,
      "best_back_price": 1.58,
      "best_back_size": 75.3
    },
    {
      "market_id": "1.259665442",
      "event_name": "Univ Catolica (Chile) v Deportes Copiapo",
      "start_time": "2026-07-05T00:30:00.000Z",
      "runner_id": 7029037,
      "best_back_price": 1.34,
      "best_back_size": 13.12
    },
    {
      "market_id": "1.259735084",
      "event_name": "Club Atletico Morelia v Cruz Azul",
      "start_time": "2026-07-05T01:30:00.000Z",
      "runner_id": 35619598,
      "best_back_price": 6.2,
      "best_back_size": 57.0
    },
    {
      "market_id": "1.259738620",
      "event_name": "Club Jaiba Brava v CF America",
      "start_time": "2026-07-05T02:00:00.000Z",
      "runner_id": 96116352,
      "best_back_price": 6.6,
      "best_back_size": 41.5
    },
    {
      "market_id": "1.259721806",
      "event_name": "Namyangju FC v Seoul Jungang FC",
      "start_time": "2026-07-05T09:00:00.000Z",
      "runner_id": 67146540,
      "best_back_price": 1.01,
      "best_back_size": 5.0
    },
    {
      "market_id": "1.259736713",
      "event_name": "Incheong Seogot v Geoje FC",
      "start_time": "2026-07-05T09:00:00.000Z",
      "runner_id": 100325670,
      "best_back_price": 1.01,
      "best_back_size": 5.0
    },
    {
      "market_id": "1.259737318",
      "event_name": "Gyeongju H&N P v Seosan FC",
      "start_time": "2026-07-05T10:00:00.000Z",
      "runner_id": 73285338,
      "best_back_price": 1.01,
      "best_back_size": 5.0
    },
    {
      "market_id": "1.259721559",
      "event_name": "Busan Transportation Corp v Gijang United",
      "start_time": "2026-07-05T10:00:00.000Z",
      "runner_id": 14163797,
      "best_back_price": 1.17,
      "best_back_size": 13.5
    },
    {
      "market_id": "1.259721947",
      "event_name": "Pyeongtaek Citizen v Yeoju FC",
      "start_time": "2026-07-05T10:00:00.000Z",
      "runner_id": 26157426,
      "best_back_price": 1.01,
      "best_back_size": 5.0
    },
    {
      "market_id": "1.259673554",
      "event_name": "Gimhae City v Seoul E-Land FC",
      "start_time": "2026-07-05T10:30:00.000Z",
      "runner_id": 13494268,
      "best_back_price": 6.2,
      "best_back_size": 45.0
    },
    {
      "market_id": "1.259674067",
      "event_name": "Gimpo Citizen v Chungnam Asan",
      "start_time": "2026-07-05T10:30:00.000Z",
      "runner_id": 19825802,
      "best_back_price": 1.92,
      "best_back_size": 154.5
    },
    {
      "market_id": "1.259674088",
      "event_name": "Jeonnam Dragons v Busan IPark",
      "start_time": "2026-07-05T10:30:00.000Z",
      "runner_id": 8349517,
      "best_back_price": 3.25,
      "best_back_size": 58.5
    },
    {
      "market_id": "1.259573875",
      "event_name": "Gwangju FC v Ulsan Hyundai Horang-i",
      "start_time": "2026-07-05T10:30:00.000Z",
      "runner_id": 5348611,
      "best_back_price": 7.6,
      "best_back_size": 37.61
    },
    {
      "market_id": "1.259683418",
      "event_name": "FC Seoul v Incheon Utd",
      "start_time": "2026-07-05T10:30:00.000Z",
      "runner_id": 2479786,
      "best_back_price": 1.97,
      "best_back_size": 164.38
    },
    {
      "market_id": "1.259573938",
      "event_name": "Gimcheon Sangmu v Jeju Utd",
      "start_time": "2026-07-05T10:30:00.000Z",
      "runner_id": 41053763,
      "best_back_price": 2.54,
      "best_back_size": 73.0
    },
    {
      "market_id": "1.259674046",
      "event_name": "Gyeongnam v Cheonan City",
      "start_time": "2026-07-05T10:30:00.000Z",
      "runner_id": 5293481,
      "best_back_price": 2.64,
      "best_back_size": 78.5
    },
    {
      "market_id": "1.259673355",
      "event_name": "Qingdao Hainiu v Chengdu Rongcheng",
      "start_time": "2026-07-05T11:00:00.000Z",
      "runner_id": 9654927,
      "best_back_price": 5.5,
      "best_back_size": 47.22
    },
    {
      "market_id": "1.259739958",
      "event_name": "Union St Gilloise v FCSB",
      "start_time": "2026-07-05T11:00:00.000Z",
      "runner_id": 892024,
      "best_back_price": 1.01,
      "best_back_size": 5.0
    },
    {
      "market_id": "1.259673334",
      "event_name": "Shanghai Shenhua v Zhejiang Greentown",
      "start_time": "2026-07-05T11:35:00.000Z",
      "runner_id": 1550828,
      "best_back_price": 1.73,
      "best_back_size": 289.17
    },
    {
      "market_id": "1.259689689",
      "event_name": "Kalmar FF v Orgryte",
      "start_time": "2026-07-05T12:00:00.000Z",
      "runner_id": 130433,
      "best_back_price": 1.53,
      "best_back_size": 225.98
    },
    {
      "market_id": "1.259573896",
      "event_name": "IFK Goteborg v AIK",
      "start_time": "2026-07-05T12:00:00.000Z",
      "runner_id": 30689,
      "best_back_price": 2.2,
      "best_back_size": 176.99
    },
    {
      "market_id": "1.259701638",
      "event_name": "Flora Tallinn II v Levadia Tallinn II",
      "start_time": "2026-07-05T12:00:00.000Z",
      "runner_id": 5412351,
      "best_back_price": 1.01,
      "best_back_size": 5.0
    },
    {
      "market_id": "1.259703173",
      "event_name": "Nomme Kalju II v FC Elva",
      "start_time": "2026-07-05T12:00:00.000Z",
      "runner_id": 10396212,
      "best_back_price": 1.01,
      "best_back_size": 5.0
    },
    {
      "market_id": "1.259739916",
      "event_name": "AGF v Motherwell",
      "start_time": "2026-07-05T12:00:00.000Z",
      "runner_id": 28214,
      "best_back_price": 1.01,
      "best_back_size": 5.0
    },
    {
      "market_id": "1.259741112",
      "event_name": "TPV v JJK",
      "start_time": "2026-07-05T12:00:00.000Z",
      "runner_id": 804682,
      "best_back_price": 4.6,
      "best_back_size": 53.0
    },
    {
      "market_id": "1.259739937",
      "event_name": "RKAV Volendam v FC Volendam",
      "start_time": "2026-07-05T12:30:00.000Z",
      "runner_id": 20254133,
      "best_back_price": 1.01,
      "best_back_size": 5.0
    },
    {
      "market_id": "1.259633311",
      "event_name": "SC Grobina v FK Tukums 2000",
      "start_time": "2026-07-05T13:00:00.000Z",
      "runner_id": 11279685,
      "best_back_price": 2.12,
      "best_back_size": 173.0
    },
    {
      "market_id": "1.259739895",
      "event_name": "Rapid Vienna v Pardubice",
      "start_time": "2026-07-05T13:00:00.000Z",
      "runner_id": 46932,
      "best_back_price": 1.01,
      "best_back_size": 5.0
    },
    {
      "market_id": "1.259703131",
      "event_name": "RoPS v PKK-U",
      "start_time": "2026-07-05T13:00:00.000Z",
      "runner_id": 396725,
      "best_back_price": 1.63,
      "best_back_size": 21.5
    },
    {
      "market_id": "1.259739979",
      "event_name": "Rosenborg v Molde",
      "start_time": "2026-07-05T13:30:00.000Z",
      "runner_id": 55224,
      "best_back_price": 1.01,
      "best_back_size": 5.0
    },
    {
      "market_id": "1.259673444",
      "event_name": "Odds BK v Haugesund",
      "start_time": "2026-07-05T14:00:00.000Z",
      "runner_id": 10833201,
      "best_back_price": 2.28,
      "best_back_size": 116.5
    },
    {
      "market_id": "1.259573917",
      "event_name": "Elfsborg v Hammarby",
      "start_time": "2026-07-05T14:30:00.000Z",
      "runner_id": 30684,
      "best_back_price": 4.0,
      "best_back_size": 127.36
    },
    {
      "market_id": "1.259739434",
      "event_name": "Union Sportive Boujaad v Racing de Casablanca",
      "start_time": "2026-07-05T15:00:00.000Z",
      "runner_id": 90656543,
      "best_back_price": 1.01,
      "best_back_size": 5.0
    },
    {
      "market_id": "1.259739301",
      "event_name": "SCCM Chabab Mohamedia v KAC Kenitra",
      "start_time": "2026-07-05T15:00:00.000Z",
      "runner_id": 25848557,
      "best_back_price": 1.01,
      "best_back_size": 5.0
    },
    {
      "market_id": "1.259733060",
      "event_name": "CC Riadi Salmi v Chabab Ben Guerir",
      "start_time": "2026-07-05T15:00:00.000Z",
      "runner_id": 14340575,
      "best_back_price": 1.01,
      "best_back_size": 5.0
    },
    {
      "market_id": "1.259726024",
      "event_name": "Serbia U19 v Croatia U19",
      "start_time": "2026-07-05T15:00:00.000Z",
      "runner_id": 2122602,
      "best_back_price": 4.0,
      "best_back_size": 37.5
    },
    {
      "market_id": "1.259733038",
      "event_name": "Widad Temara v USM Oujda",
      "start_time": "2026-07-05T15:00:00.000Z",
      "runner_id": 10645503,
      "best_back_price": 1.01,
      "best_back_size": 5.0
    },
    {
      "market_id": "1.259735319",
      "event_name": "Chabab Atlas Khenifra v US Amal Tiznit",
      "start_time": "2026-07-05T15:00:00.000Z",
      "runner_id": 8184403,
      "best_back_price": 1.01,
      "best_back_size": 5.0
    },
    {
      "market_id": "1.259726045",
      "event_name": "Ukraine U19 v Italy U19",
      "start_time": "2026-07-05T15:00:00.000Z",
      "runner_id": 865348,
      "best_back_price": 3.85,
      "best_back_size": 24.5
    },
    {
      "market_id": "1.259742060",
      "event_name": "Rapid Vienna v Rapid Bucharest",
      "start_time": "2026-07-05T15:15:00.000Z",
      "runner_id": 46932,
      "best_back_price": 1.01,
      "best_back_size": 5.0
    },
    {
      "market_id": "1.259684069",
      "event_name": "Fk Siauliai v VMFD Zalgiris",
      "start_time": "2026-07-05T15:45:00.000Z",
      "runner_id": 23642514,
      "best_back_price": 3.05,
      "best_back_size": 12.0
    },
    {
      "market_id": "1.259740376",
      "event_name": "Sportivo Italiano v Real Pilar FC",
      "start_time": "2026-07-05T16:00:00.000Z",
      "runner_id": 5971717,
      "best_back_price": 2.26,
      "best_back_size": 63.5
    },
    {
      "market_id": "1.259684384",
      "event_name": "Tammeka Tartu v Harju JK Laagri",
      "start_time": "2026-07-05T16:00:00.000Z",
      "runner_id": 5407303,
      "best_back_price": 1.78,
      "best_back_size": 27.0
    },
    {
      "market_id": "1.259707726",
      "event_name": "La Serena v Antofagasta",
      "start_time": "2026-07-05T16:30:00.000Z",
      "runner_id": 5129868,
      "best_back_price": 1.96,
      "best_back_size": 137.5
    },
    {
      "market_id": "1.259707524",
      "event_name": "Santiago Wanderers v Universidad de Chile",
      "start_time": "2026-07-05T16:30:00.000Z",
      "runner_id": 913363,
      "best_back_price": 4.4,
      "best_back_size": 46.0
    },
    {
      "market_id": "1.259733398",
      "event_name": "FAR Rabat v Club R Zemamra",
      "start_time": "2026-07-05T17:00:00.000Z",
      "runner_id": 6670769,
      "best_back_price": 1.38,
      "best_back_size": 61.5
    },
    {
      "market_id": "1.259726003",
      "event_name": "Olympic Safi v Raja Casablanca",
      "start_time": "2026-07-05T17:00:00.000Z",
      "runner_id": 6666958,
      "best_back_price": 5.7,
      "best_back_size": 14.5
    },
    {
      "market_id": "1.259733357",
      "event_name": "DHJ El Jadida v RSB Berkane",
      "start_time": "2026-07-05T17:00:00.000Z",
      "runner_id": 6845213,
      "best_back_price": 1.01,
      "best_back_size": 13.91
    },
    {
      "market_id": "1.259724901",
      "event_name": "Wydad Casablanca v Union de Touarga",
      "start_time": "2026-07-05T17:00:00.000Z",
      "runner_id": 4018643,
      "best_back_price": 2.3,
      "best_back_size": 35.0
    },
    {
      "market_id": "1.259724922",
      "event_name": "IRT Tanger v CODM Meknes",
      "start_time": "2026-07-05T17:00:00.000Z",
      "runner_id": 13111553,
      "best_back_price": 2.26,
      "best_back_size": 18.5
    },
    {
      "market_id": "1.259733312",
      "event_name": "MAS Maghrib A Fes v Olympique Dcheira",
      "start_time": "2026-07-05T17:00:00.000Z",
      "runner_id": 16530095,
      "best_back_price": 1.51,
      "best_back_size": 12.0
    },
    {
      "market_id": "1.259724859",
      "event_name": "HUSA Agadir v Kawkab Marrakech",
      "start_time": "2026-07-05T17:00:00.000Z",
      "runner_id": 6360286,
      "best_back_price": 1.82,
      "best_back_size": 28.5
    },
    {
      "market_id": "1.259724880",
      "event_name": "FUS Rabat v Yacoub El Mansour",
      "start_time": "2026-07-05T17:00:00.000Z",
      "runner_id": 6681575,
      "best_back_price": 3.25,
      "best_back_size": 20.5
    },
    {
      "market_id": "1.259687072",
      "event_name": "Danubio v Juventud De Las Piedras",
      "start_time": "2026-07-05T17:00:00.000Z",
      "runner_id": 504779,
      "best_back_price": 2.68,
      "best_back_size": 22.5
    },
    {
      "market_id": "1.259740623",
      "event_name": "Defensores Unidos v Argentino de Merlo",
      "start_time": "2026-07-05T18:00:00.000Z",
      "runner_id": 7108515,
      "best_back_price": 2.82,
      "best_back_size": 20.5
    },
    {
      "market_id": "1.259740644",
      "event_name": "San Martin de Burzaco v CSD Liniers de Ciudad Evi",
      "start_time": "2026-07-05T18:00:00.000Z",
      "runner_id": 9518488,
      "best_back_price": 2.26,
      "best_back_size": 185.5
    },
    {
      "market_id": "1.259700374",
      "event_name": "Estudiantes de Caseros v Club Atletico Racing de ",
      "start_time": "2026-07-05T18:00:00.000Z",
      "runner_id": 7546748,
      "best_back_price": 1.01,
      "best_back_size": 3.0
    },
    {
      "market_id": "1.259688058",
      "event_name": "Deportivo Madryn v Colon",
      "start_time": "2026-07-05T18:00:00.000Z",
      "runner_id": 10995035,
      "best_back_price": 2.32,
      "best_back_size": 163.0
    },
    {
      "market_id": "1.259689797",
      "event_name": "Macara v LDU",
      "start_time": "2026-07-05T18:00:00.000Z",
      "runner_id": 6161547,
      "best_back_price": 3.5,
      "best_back_size": 58.5
    },
    {
      "market_id": "1.259688143",
      "event_name": "Ferro Carril Oeste v San Telmo",
      "start_time": "2026-07-05T18:30:00.000Z",
      "runner_id": 5985279,
      "best_back_price": 1.63,
      "best_back_size": 223.0
    },
    {
      "market_id": "1.259688129",
      "event_name": "Patronato v San Martin de Tucuman",
      "start_time": "2026-07-05T18:30:00.000Z",
      "runner_id": 5178628,
      "best_back_price": 2.46,
      "best_back_size": 160.0
    },
    {
      "market_id": "1.259708201",
      "event_name": "Nublense v Curico Unido",
      "start_time": "2026-07-05T19:00:00.000Z",
      "runner_id": 3303740,
      "best_back_price": 1.56,
      "best_back_size": 13.0
    },
    {
      "market_id": "1.259688450",
      "event_name": "San Martin De San Juan v Chacarita",
      "start_time": "2026-07-05T19:00:00.000Z",
      "runner_id": 13140404,
      "best_back_price": 1.87,
      "best_back_size": 119.0
    },
    {
      "market_id": "1.259708264",
      "event_name": "Cobresal v Cobreloa Calama",
      "start_time": "2026-07-05T19:00:00.000Z",
      "runner_id": 5129865,
      "best_back_price": 2.0,
      "best_back_size": 105.5
    },
    {
      "market_id": "1.259708180",
      "event_name": "Univ de Concepcion v CSD Rangers",
      "start_time": "2026-07-05T19:00:00.000Z",
      "runner_id": 5129867,
      "best_back_price": 1.93,
      "best_back_size": 120.51
    },
    {
      "market_id": "1.259688464",
      "event_name": "Club Atletico Mitre v All Boys",
      "start_time": "2026-07-05T19:00:00.000Z",
      "runner_id": 14926119,
      "best_back_price": 2.16,
      "best_back_size": 100.5
    },
    {
      "market_id": "1.259708243",
      "event_name": "Puerto Montt v Huachipato",
      "start_time": "2026-07-05T19:00:00.000Z",
      "runner_id": 5684078,
      "best_back_price": 2.88,
      "best_back_size": 66.5
    },
    {
      "market_id": "1.259688436",
      "event_name": "FC Midland v Gimnasia Jujuy",
      "start_time": "2026-07-05T19:00:00.000Z",
      "runner_id": 9518489,
      "best_back_price": 2.46,
      "best_back_size": 160.0
    },
    {
      "market_id": "1.259688979",
      "event_name": "CA Central Norte v CA San Miguel",
      "start_time": "2026-07-05T19:30:00.000Z",
      "runner_id": 8278454,
      "best_back_price": 2.44,
      "best_back_size": 143.0
    },
    {
      "market_id": "1.259689083",
      "event_name": "CD Maipu v Agropecuario",
      "start_time": "2026-07-05T19:30:00.000Z",
      "runner_id": 10723921,
      "best_back_price": 2.16,
      "best_back_size": 58.5
    },
    {
      "market_id": "1.259708159",
      "event_name": "Club Deportes Santa Cruz v Audax Italiano",
      "start_time": "2026-07-05T20:00:00.000Z",
      "runner_id": 11023627,
      "best_back_price": 2.84,
      "best_back_size": 20.0
    },
    {
      "market_id": "1.259628052",
      "event_name": "Brazil v Norway",
      "start_time": "2026-07-05T20:00:00.000Z",
      "runner_id": 1408,
      "best_back_price": 1.9,
      "best_back_size": 858.1
    },
    {
      "market_id": "1.259708222",
      "event_name": "Union Espanola v OHiggins",
      "start_time": "2026-07-05T21:30:00.000Z",
      "runner_id": 1388376,
      "best_back_price": 3.2,
      "best_back_size": 78.0
    },
    {
      "market_id": "1.259645190",
      "event_name": "Delfin v Emelec",
      "start_time": "2026-07-05T22:00:00.000Z",
      "runner_id": 10778437,
      "best_back_price": 2.8,
      "best_back_size": 13.0
    },
    {
      "market_id": "1.259573854",
      "event_name": "Nautico PE v Juventude",
      "start_time": "2026-07-05T23:30:00.000Z",
      "runner_id": 7210009,
      "best_back_price": 2.28,
      "best_back_size": 67.0
    },
    {
      "market_id": "1.259657056",
      "event_name": "Mexico v England",
      "start_time": "2026-07-06T00:00:00.000Z",
      "runner_id": 37944,
      "best_back_price": 3.25,
      "best_back_size": 1573.0
    },
    {
      "market_id": "1.259714657",
      "event_name": "FK Suduva v TransINVEST Vilnius",
      "start_time": "2026-07-06T15:45:00.000Z",
      "runner_id": 198707,
      "best_back_price": 2.32,
      "best_back_size": 177.0
    },
    {
      "market_id": "1.259663283",
      "event_name": "SK Super Nova v Ogre United",
      "start_time": "2026-07-06T16:00:00.000Z",
      "runner_id": 19582511,
      "best_back_price": 1.01,
      "best_back_size": 5.0
    },
    {
      "market_id": "1.259599929",
      "event_name": "Hacken v Djurgardens",
      "start_time": "2026-07-06T17:00:00.000Z",
      "runner_id": 30681,
      "best_back_price": 2.44,
      "best_back_size": 20.88
    },
    {
      "market_id": "1.259599908",
      "event_name": "Brommapojkarna v GAIS",
      "start_time": "2026-07-06T17:00:00.000Z",
      "runner_id": 151472,
      "best_back_price": 3.35,
      "best_back_size": 19.61
    },
    {
      "market_id": "1.259691614",
      "event_name": "Portugal v Spain",
      "start_time": "2026-07-06T19:00:00.000Z",
      "runner_id": 19,
      "best_back_price": 4.3,
      "best_back_size": 20.5
    },
    {
      "market_id": "1.259689767",
      "event_name": "Univ Catolica (Ecu) v Mushuc Runa",
      "start_time": "2026-07-06T21:30:00.000Z",
      "runner_id": 7005170,
      "best_back_price": 1.55,
      "best_back_size": 327.5
    },
    {
      "market_id": "1.259689818",
      "event_name": "Orense Sporting Club v Tecnico Universitario",
      "start_time": "2026-07-07T00:00:00.000Z",
      "runner_id": 17583926,
      "best_back_price": 1.83,
      "best_back_size": 259.0
    },
    {
      "market_id": "1.259667198",
      "event_name": "USA v Belgium",
      "start_time": "2026-07-07T00:00:00.000Z",
      "runner_id": 352,
      "best_back_price": 2.82,
      "best_back_size": 825.01
    },
    {
      "market_id": "1.259723983",
      "event_name": "Argentina v Egypt",
      "start_time": "2026-07-07T16:00:00.000Z",
      "runner_id": 55212,
      "best_back_price": 1.39,
      "best_back_size": 4192.8
    },
    {
      "market_id": "1.259725394",
      "event_name": "Switzerland v Colombia",
      "start_time": "2026-07-07T20:00:00.000Z",
      "runner_id": 15293,
      "best_back_price": 3.65,
      "best_back_size": 806.0
    },
    {
      "market_id": "1.259689902",
      "event_name": "Aucas v Guayaquil City",
      "start_time": "2026-07-08T00:00:00.000Z",
      "runner_id": 897347,
      "best_back_price": 1.4,
      "best_back_size": 50.0
    },
    {
      "market_id": "1.259721969",
      "event_name": "Deportivo Maldonado v Albion FC",
      "start_time": "2026-07-10T22:00:00.000Z",
      "runner_id": 10932747,
      "best_back_price": 1.01,
      "best_back_size": 3.0
    }
  ]
}